Workbook

Sheet README
A1: THE SOUTH AFRICA RATES LIBRARY — MASTER SHEET
A2: Library ref SA-RL-2609-01 | Base date September 2026 | Base region Gauteng | Currency ZAR
A4: WHAT THE RATES ARE
A5: Every unit rate on the Rates sheet is a NET cost build-up: labour (gang-hours x all-in gang rate) + materials (quantity incl. waste x delivered price) + sundries + plant.
A6: Net rates EXCLUDE contractor margin and EXCLUDE VAT. Column T applies the region factor and escalation; column U adds the margin on the Settings sheet (17%).
A7: VAT (15%) is added once, at the foot of the BOQ, not in the rates.
A9: HOW TO USE ON A JOB
A10: 1. Settings: pick the region from the drop-down and enter the tender / start date. Region factor and escalation flow into every rate.
A11: 2. Price the BOQ from Rates column U (sell, ex VAT) or column T (net) if the margin is applied at summary level.
A12: 3. Sanity-check the total against the Elemental sheet (AECOM R/m2 benchmarks, escalated).
A13: 4. Where the contractor supplies invoices or their own rates, overwrite the blue input cells on Materials / Labour / Plant — every rate re-builds automatically.
A15: COLOUR KEY
... A26: Replace QS ESTIMATE lines with real contractor invoice prices as SA jobs come in — the library is built to be tightened that way.

Sheet Settings
A1: SETTINGS — set per job
A3: Region (select) | B3: Gauteng (Johannesburg / Pretoria / Midrand) - BASE | C3: Drop-down. Drives the region factor.
A4: Region factor | B4: =INDEX(Regions!$B:$B,MATCH(B3,Regions!$A:$A,0)) -> 1 | C4: Looked up from Regions sheet.
A5: Library base date | B5: 46266 | C5: Resource prices current at this date.
A6: Tender / start date | B6: 46266 | C6: Enter the job's expected tender or start date.
A7: Forward escalation p.a. | B7: 0.047 | C7: BER tender-price forecast 2027 +4.7% (AECOM Cost Guide 2025/26, Section 7).
A8: Months forward | B8: =MAX(0,(YEAR(B6)-YEAR(B5))*12+MONTH(B6)-MONTH(B5)) -> 0 | C8: Formula.
A9: Escalation factor | B9: =(1+B7)^(B8/12) -> 1 | C9: Compounded from base date to tender date.
A10: Contractor margin (profit) | B10: 0.17 | C10: AI QS standing rule: 17% on all jobs.
A11: VAT | B11: 0.15 | C11: SA VAT 15% — apply at BOQ foot only.
A13: LABOUR ON-COSTS (on basic wage)
A14: Statutory (UIF 1%, SDL 1%, COIDA ~2.5%) | B14: 0.045 | C14: Unemployment Insurance Act, Skills Development Levies Act, COIDA building class estimate.
A15: Leave, public holidays, sick leave, bonus | B15: 0.14 | C15: BCEA entitlements + bargaining council bonus fund equivalent.
A16: Non-productive time, travel, PPE, small tools | B16: 0.1 | C16: QS estimate.
A17: TOTAL ON-COST | B17: =SUM(B14:B16) -> 0.285 | C17: Formula — used by Labour sheet.

Sheet Rates
A1: SOUTH AFRICA UNIT RATES — SA-RL-2609-01
A2: ="Region: "&Settings!$B$3&" | Factor "&TEXT(Settings!$B$4,"0.00")&" | Escalation "&TEXT(Settings!$B$9,"0.0000")&" | Margin "&TEXT(Settings!$B$10,"0%")&" | All rates ex VAT" -> Region: Gauteng (Johannesburg / Pretoria / Midrand) - BASE | Factor 1.00 | Escalation 1.0000 | Margin 17% | All rates ex VAT
A4: Code | B4: Description | C4: Unit | D4: Gang | E4: Gang-hrs / unit | F4: Labour R | G4: Mat 1 | H4: Qty 1 | I4: Mat 2 | J4: Qty 2 | K4: Mat 3 | L4: Qty 3 | M4: Materials R | N4: Sundries R | O4: Plant | P4: Plant qty | Q4: Plant R | R4: NET rate R (Gauteng base) | S4: NET rate R (region + escalation) | T4: SELL rate R incl margin, ex VAT
A5: PRELIMINARIES & GENERAL
A6: PR01 | B6: Site establishment & de-establishment, small works (hoarding, signage, set-up) | C6: item | D6: G-LAB | E6: 16 | F6: =IF(D6="",0,E6*INDEX(Gangs!$D:$D,MATCH(D6,Gangs!$A:$A,0))) -> 849.7448 | M6: =IF(G6="",0,H6*INDEX(Materials!$E:$E,MATCH(G6,Materials!$A:$A,0)))+IF(I6="",0,J6*INDEX(Materials!$E:$E,MATCH(I6,Materials!$A:$A,0)))+IF(K6="",0,L6*INDEX(Materials!$E:$E,MATCH(K6,Materials!$A:$A,0))) -> 0 | N6: 9500 | Q6: =IF(O6="",0,P6*INDEX(Plant!$D:$D,MATCH(O6,Plant!$A:$A,0))) -> 0 | R6: =F6+M6+N6+Q6 -> 10349.745 | S6: =R6*Settings!$B$4*Settings!$B$9 -> 10349.745 | T6: =S6*(1+Settings!$B$10) -> 12109.201
A7: PR02 | B7: Site foreman, full time | C7: week | D7: G-FMN | E7: 45 | F7: =IF(D7="",0,E7*INDEX(Gangs!$D:$D,MATCH(D7,Gangs!$A:$A,0))) -> 8673.75 | M7: =IF(G7="",0,H7*INDEX(Materials!$E:$E,MATCH(G7,Materials!$A:$A,0)))+IF(I7="",0,J7*INDEX(Materials!$E:$E,MATCH(I7,Materials!$A:$A,0)))+IF(K7="",0,L7*INDEX(Materials!$E:$E,MATCH(K7,Materials!$A:$A,0))) -> 0 | N7: 0 | Q7: =IF(O7="",0,P7*INDEX(Plant!$D:$D,MATCH(O7,Plant!$A:$A,0))) -> 0 | R7: =F7+M7+N7+Q7 -> 8673.75 | S7: =R7*Settings!$B$4*Settings!$B$9 -> 8673.75 | T7: =S7*(1+Settings!$B$10) -> 10148.288
A8: PR03 | B8: Site agent, one day per week | C8: week | D8: G-SA | E8: 9 | F8: =IF(D8="",0,E8*INDEX(Gangs!$D:$D,MATCH(D8,Gangs!$A:$A,0))) -> 2775.6 | M8: =IF(G8="",0,H8*INDEX(Materials!$E:$E,MATCH(G8,Materials!$A:$A,0)))+IF(I8="",0,J8*INDEX(Materials!$E:$E,MATCH(I8,Materials!$A:$A,0)))+IF(K8="",0,L8*INDEX(Materials!$E:$E,MATCH(K8,Materials!$A:$A,0))) -> 0 | N8: 0 | Q8: =IF(O8="",0,P8*INDEX(Plant!$D:$D,MATCH(O8,Plant!$A:$A,0))) -> 0 | R8: =F8+M8+N8+Q8 -> 2775.6 | S8: =R8*Settings!$B$4*Settings!$B$9 -> 2775.6 | T8: =S8*(1+Settings!$B$10) -> 3247.452
A9: PR04 | B9: Chemical toilet incl servicing | C9: week | F9: =IF(D9="",0,E9*INDEX(Gangs!$D:$D,MATCH(D9,Gangs!$A:$A,0))) -> 0 | M9: =IF(G9="",0,H9*INDEX(Materials!$E:$E,MATCH(G9,Materials!$A:$A,0)))+IF(I9="",0,J9*INDEX(Materials!$E:$E,MATCH(I9,Materials!$A:$A,0)))+IF(K9="",0,L9*INDEX(Materials!$E:$E,MATCH(K9,Materials!$A:$A,0))) -> 0 | N9: 0 | O9: P-TOILET | P9: 1 | Q9: =IF(O9="",0,P9*INDEX(Plant!$D:$D,MATCH(O9,Plant!$A:$A,0))) -> 650 | R9: =F9+M9+N9+Q9 -> 650 | S9: =R9*Settings!$B$4*Settings!$B$9 -> 650 | T9: =S9*(1+Settings!$B$10) -> 760.5
A10: PR05 | B10: Site office / store container | C10: week | F10: =IF(D10="",0,E10*INDEX(Gangs!$D:$D,MATCH(D10,Gangs!$A:$A,0))) -> 0 | M10: =IF(G10="",0,H10*INDEX(Materials!$E:$E,MATCH(G10,Materials!$A:$A,0)))+IF(I10="",0,J10*INDEX(Materials!$E:$E,MATCH(I10,Materials!$A:$A,0)))+IF(K10="",0,L10*INDEX(Materials!$E:$E,MATCH(K10,Materials!$A:$A,0))) -> 0 | N10: 0 | O10: P-CONT | P10: 1 | Q10: =IF(O10="",0,P10*INDEX(Plant!$D:$D,MATCH(O10,Plant!$A:$A,0))) -> 520 | R10: =F10+M10+N10+Q10 -> 520 | S10: =R10*Settings!$B$4*Settings!$B$9 -> 520 | T10: =S10*(1+Settings!$B$10) -> 608.4
A11: PR06 | B11: Temporary water & electricity (consumption) | C11: week | F11: =IF(D11="",0,E11*INDEX(Gangs!$D:$D,MATCH(D11,Gangs!$A:$A,0))) -> 0 | M11: =IF(G11="",0,H11*INDEX(Materials!$E:$E,MATCH(G11,Materials!$A:$A,0)))+IF(I11="",0,J11*INDEX(Materials!$E:$E,MATCH(I11,Materials!$A:$A,0)))+IF(K11="",0,L11*INDEX(Materials!$E:$E,MATCH(K11,Materials!$A:$A,0))) -> 0 | N11: 450 | Q11: =IF(O11="",0,P11*INDEX(Plant!$D:$D,MATCH(O11,Plant!$A:$A,0))) -> 0 | R11: =F11+M11+N11+Q11 -> 450 | S11: =R11*Settings!$B$4*Settings!$B$9 -> 450 | T11: =S11*(1+Settings!$B$10) -> 526.5
A12: PR07 | B12: Security guard, 12 h shift (Cape BIBC R495.34/day + on-costs) | C12: day | F12: =IF(D12="",0,E12*INDEX(Gangs!$D:$D,MATCH(D12,Gangs!$A:$A,0))) -> 0 | M12: =IF(G12="",0,H12*INDEX(Materials!$E:$E,MATCH(G12,Materials!$A:$A,0)))+IF(I12="",0,J12*INDEX(Materials!$E:$E,MATCH(I12,Materials!$A:$A,0)))+IF(K12="",0,L12*INDEX(Materials!$E:$E,MATCH(K12,Materials!$A:$A,0))) -> 0 | N12: 640 | Q12: =IF(O12="",0,P12*INDEX(Plant!$D:$D,MATCH(O12,Plant!$A:$A,0))) -> 0 | R12: =F12+M12+N12+Q12 -> 640 | S12: =R12*Settings!$B$4*Settings!$B$9 -> 640 | T12: =S12*(1+Settings!$B$10) -> 748.8
A13: PR08 | B13: Skip 6 m3 incl removal | C13: no | F13: =IF(D13="",0,E13*INDEX(Gangs!$D:$D,MATCH(D13,Gangs!$A:$A,0))) -> 0 | M13: =IF(G13="",0,H13*INDEX(Materials!$E:$E,MATCH(G13,Materials!$A:$A,0)))+IF(I13="",0,J13*INDEX(Materials!$E:$E,MATCH(I13,Materials!$A:$A,0)))+IF(K13="",0,L13*INDEX(Materials!$E:$E,MATCH(K13,Materials!$A:$A,0))) -> 0 | N13: 0 | O13: P-SKIP | P13: 1 | Q13: =IF(O13="",0,P13*INDEX(Plant!$D:$D,MATCH(O13,Plant!$A:$A,0))) -> 2300 | R13: =F13+M13+N13+Q13 -> 2300 | S13: =R13*Settings!$B$4*Settings!$B$9 -> 2300 | T13: =S13*(1+Settings!$B$10) -> 2691
A14: PR09 | B14: Health & Safety file, plan & baseline risk assessment (Construction Regs 2014) | C14: item | F14: =IF(D14="",0,E14*INDEX(Gangs!$D:$D,MATCH(D14,Gangs!$A:$A,0))) -> 0 | M14: =IF(G14="",0,H14*INDEX(Materials!$E:$E,MATCH(G14,Materials!$A:$A,0)))+IF(I14="",0,J14*INDEX(Materials!$E:$E,MATCH(I14,Materials!$A:$A,0)))+IF(K14="",0,L14*INDEX(Materials!$E:$E,MATCH(K14,Materials!$A:$A,0))) -> 0 | N14: 9500 | Q14: =IF(O14="",0,P14*INDEX(Plant!$D:$D,MATCH(O14,Plant!$A:$A,0))) -> 0 | R14: =F14+M14+N14+Q14 -> 9500 | S14: =R14*Settings!$B$4*Settings!$B$9 -> 9500 | T14: =S14*(1+Settings!$B$10) -> 11115
A15: PR10 | B15: Electrical Certificate of Compliance (COC) | C15: item | F15: =IF(D15="",0,E15*INDEX(Gangs!$D:$D,MATCH(D15,Gangs!$A:$A,0))) -> 0 | M15: =IF(G15="",0,H15*INDEX(Materials!$E:$E,MATCH(G15,Materials!$A:$A,0)))+IF(I15="",0,J15*INDEX(Materials!$E:$E,MATCH(I15,Materials!$A:$A,0)))+IF(K15="",0,L15*INDEX(Materials!$E:$E,MATCH(K15,Materials!$A:$A,0))) -> 0 | N15: 3200 | Q15: =IF(O15="",0,P15*INDEX(Plant!$D:$D,MATCH(O15,Plant!$A:$A,0))) -> 0 | R15: =F15+M15+N15+Q15 -> 3200 | S15: =R15*Settings!$B$4*Settings!$B$9 -> 3200 | T15: =S15*(1+Settings!$B$10) -> 3744
A16: PR11 | B16: Plumbing Certificate of Compliance (PIRB) | C16: item | F16: =IF(D16="",0,E16*INDEX(Gangs!$D:$D,MATCH(D16,Gangs!$A:$A,0))) -> 0 | M16: =IF(G16="",0,H16*INDEX(Materials!$E:$E,MATCH(G16,Materials!$A:$A,0)))+IF(I16="",0,J16*INDEX(Materials!$E:$E,MATCH(I16,Materials!$A:$A,0)))+IF(K16="",0,L16*INDEX(Materials!$E:$E,MATCH(K16,Materials!$A:$A,0))) -> 0 | N16: 1800 | Q16: =IF(O16="",0,P16*INDEX(Plant!$D:$D,MATCH(O16,Plant!$A:$A,0))) -> 0 | R16: =F16+M16+N16+Q16 -> 1800 | S16: =R16*Settings!$B$4*Settings!$B$9 -> 1800 | T16: =S16*(1+Settings!$B$10) -> 2106
A17: PR12 | B17: Setting out by land surveyor, small building | C17: item | F17: =IF(D17="",0,E17*INDEX(Gangs!$D:$D,MATCH(D17,Gangs!$A:$A,0))) -> 0 | M17: =IF(G17="",0,H17*INDEX(Materials!$E:$E,MATCH(G17,Materials!$A:$A,0)))+IF(I17="",0,J17*INDEX(Materials!$E:$E,MATCH(I17,Materials!$A:$A,0)))+IF(K17="",0,L17*INDEX(Materials!$E:$E,MATCH(K17,Materials!$A:$A,0))) -> 0 | N17: 6500 | Q17: =IF(O17="",0,P17*INDEX(Plant!$D:$D,MATCH(O17,Plant!$A:$A,0))) -> 0 | R17: =F17+M17+N17+Q17 -> 6500 | S17: =R17*Settings!$B$4*Settings!$B$9 -> 6500 | T17: =S17*(1+Settings!$B$10) -> 7605
A18: PR13 | B18: Builder's clean on completion | C18: m2 | D18: G-LAB | E18: 0.12 | F18: =IF(D18="",0,E18*INDEX(Gangs!$D:$D,MATCH(D18,Gangs!$A:$A,0))) -> 6.373086 | M18: =IF(G18="",0,H18*INDEX(Materials!$E:$E,MATCH(G18,Materials!$A:$A,0)))+IF(I18="",0,J18*INDEX(Materials!$E:$E,MATCH(I18,Materials!$A:$A,0)))+IF(K18="",0,L18*INDEX(Materials!$E:$E,MATCH(K18,Materials!$A:$A,0))) -> 0 | N18: 4 | Q18: =IF(O18="",0,P18*INDEX(Plant!$D:$D,MATCH(O18,Plant!$A:$A,0))) -> 0 | R18: =F18+M18+N18+Q18 -> 10.373086 | S18: =R18*Settings!$B$4*Settings!$B$9 -> 10.373086 | T18: =S18*(1+Settings!$B$10) -> 12.136511
A19: PR14 | B19: Frame scaffold hire | C19: m2/wk | F19: =IF(D19="",0,E19*INDEX(Gangs!$D:$D,MATCH(D19,Gangs!$A:$A,0))) -> 0 | M19: =IF(G19="",0,H19*INDEX(Materials!$E:$E,MATCH(G19,Materials!$A:$A,0)))+IF(I19="",0,J19*INDEX(Materials!$E:$E,MATCH(I19,Materials!$A:$A,0)))+IF(K19="",0,L19*INDEX(Materials!$E:$E,MATCH(K19,Materials!$A:$A,0))) -> 0 | N19: 0 | O19: P-SCAF | P19: 1 | Q19: =IF(O19="",0,P19*INDEX(Plant!$D:$D,MATCH(O19,Plant!$A:$A,0))) -> 18 | R19: =F19+M19+N19+Q19 -> 18 | S19: =R19*Settings!$B$4*Settings!$B$9 -> 18 | T19: =S19*(1+Settings!$B$10) -> 21.06
A20: PR15 | B20: Scaffold erect & dismantle | C20: m2 | D20: G-LAB | E20: 0.25 | F20: =IF(D20="",0,E20*INDEX(Gangs!$D:$D,MATCH(D20,Gangs!$A:$A,0))) -> 13.277263 | M20: =IF(G20="",0,H20*INDEX(Materials!$E:$E,MATCH(G20,Materials!$A:$A,0)))+IF(I20="",0,J20*INDEX(Materials!$E:$E,MATCH(I20,Materials!$A:$A,0)))+IF(K20="",0,L20*INDEX(Materials!$E:$E,MATCH(K20,Materials!$A:$A,0))) -> 0 | N20: 0 | Q20: =IF(O20="",0,P20*INDEX(Plant!$D:$D,MATCH(O20,Plant!$A:$A,0))) -> 0 | R20: =F20+M20+N20+Q20 -> 13.277263 | S20: =R20*Settings!$B$4*Settings!$B$9 -> 13.277263 | T20: =S20*(1+Settings!$B$10) -> 15.534397
A21: PR16 | B21: Temporary site fencing hire | C21: m/wk | F21: =IF(D21="",0,E21*INDEX(Gangs!$D:$D,MATCH(D21,Gangs!$A:$A,0))) -> 0 | M21: =IF(G21="",0,H21*INDEX(Materials!$E:$E,MATCH(G21,Materials!$A:$A,0)))+IF(I21="",0,J21*INDEX(Materials!$E:$E,MATCH(I21,Materials!$A:$A,0)))+IF(K21="",0,L21*INDEX(Materials!$E:$E,MATCH(K21,Materials!$A:$A,0))) -> 0 | N21: 0 | O21: P-FENCE | P21: 1 | Q21: =IF(O21="",0,P21*INDEX(Plant!$D:$D,MATCH(O21,Plant!$A:$A,0))) -> 12 | R21: =F21+M21+N21+Q21 -> 12 | S21: =R21*Settings!$B$4*Settings!$B$9 -> 12 | T21: =S21*(1+Settings!$B$10) -> 14.04
A22: PR17 | B22: Temporary protection to finished floors | C22: m2 | D22: G-LAB | E22: 0.05 | F22: =IF(D22="",0,E22*INDEX(Gangs!$D:$D,MATCH(D22,Gangs!$A:$A,0))) -> 2.6554525 | M22: =IF(G22="",0,H22*INDEX(Materials!$E:$E,MATCH(G22,Materials!$A:$A,0)))+IF(I22="",0,J22*INDEX(Materials!$E:$E,MATCH(I22,Materials!$A:$A,0)))+IF(K22="",0,L22*INDEX(Materials!$E:$E,MATCH(K22,Materials!$A:$A,0))) -> 0 | N22: 18 | Q22: =IF(O22="",0,P22*INDEX(Plant!$D:$D,MATCH(O22,Plant!$A:$A,0))) -> 0 | R22: =F22+M22+N22+Q22 -> 20.655452 | S22: =R22*Settings!$B$4*Settings!$B$9 -> 20.655452 | T22: =S22*(1+Settings!$B$10) -> 24.166879
A23: DEMOLITIONS & ALTERATIONS
A24: DM01 | B24: Demolish half-brick wall incl plaster, stack rubble on site | C24: m2 | D24: G-DEM | E24: 0.6 | F24: =IF(D24="",0,E24*INDEX(Gangs!$D:$D,MATCH(D24,Gangs!$A:$A,0))) -> 105.15669 | M24: =IF(G24="",0,H24*INDEX(Materials!$E:$E,MATCH(G24,Materials!$A:$A,0)))+IF(I24="",0,J24*INDEX(Materials!$E:$E,MATCH(I24,Materials!$A:$A,0)))+IF(K24="",0,L24*INDEX(Materials!$E:$E,MATCH(K24,Materials!$A:$A,0))) -> 0 | N24: 10 | Q24: =IF(O24="",0,P24*INDEX(Plant!$D:$D,MATCH(O24,Plant!$A:$A,0))) -> 0 | R24: =F24+M24+N24+Q24 -> 115.15669 | S24: =R24*Settings!$B$4*Settings!$B$9 -> 115.15669 | T24: =S24*(1+Settings!$B$10) -> 134.73333
A25: DM02 | B25: Demolish one-brick wall incl plaster | C25: m2 | D25: G-DEM | E25: 1 | F25: =IF(D25="",0,E25*INDEX(Gangs!$D:$D,MATCH(D25,Gangs!$A:$A,0))) -> 175.26115 | M25: =IF(G25="",0,H25*INDEX(Materials!$E:$E,MATCH(G25,Materials!$A:$A,0)))+IF(I25="",0,J25*INDEX(Materials!$E:$E,MATCH(I25,Materials!$A:$A,0)))+IF(K25="",0,L25*INDEX(Materials!$E:$E,MATCH(K25,Materials!$A:$A,0))) -> 0 | N25: 15 | Q25: =IF(O25="",0,P25*INDEX(Plant!$D:$D,MATCH(O25,Plant!$A:$A,0))) -> 0 | R25: =F25+M25+N25+Q25 -> 190.26115 | S25: =R25*Settings!$B$4*Settings!$B$9 -> 190.26115 | T25: =S25*(1+Settings!$B$10) -> 222.60555
A26: DM03 | B26: Break up concrete surface bed <= 100 mm | C26: m2 | D26: G-DEM | E26: 0.5 | F26: =IF(D26="",0,E26*INDEX(Gangs!$D:$D,MATCH(D26,Gangs!$A:$A,0))) -> 87.630575 | M26: =IF(G26="",0,H26*INDEX(Materials!$E:$E,MATCH(G26,Materials!$A:$A,0)))+IF(I26="",0,J26*INDEX(Materials!$E:$E,MATCH(I26,Materials!$A:$A,0)))+IF(K26="",0,L26*INDEX(Materials!$E:$E,MATCH(K26,Materials!$A:$A,0))) -> 0 | N26: 0 | O26: P-JACK | P26: 0.4 | Q26: =IF(O26="",0,P26*INDEX(Plant!$D:$D,MATCH(O26,Plant!$A:$A,0))) -> 60 | R26: =F26+M26+N26+Q26 -> 147.63057 | S26: =R26*Settings!$B$4*Settings!$B$9 -> 147.63057 | T26: =S26*(1+Settings!$B$10) -> 172.72777
A27: DM04 | B27: Break up reinforced concrete | C27: m3 | D27: G-DEM | E27: 6 | F27: =IF(D27="",0,E27*INDEX(Gangs!$D:$D,MATCH(D27,Gangs!$A:$A,0))) -> 1051.5669 | M27: =IF(G27="",0,H27*INDEX(Materials!$E:$E,MATCH(G27,Materials!$A:$A,0)))+IF(I27="",0,J27*INDEX(Materials!$E:$E,MATCH(I27,Materials!$A:$A,0)))+IF(K27="",0,L27*INDEX(Materials!$E:$E,MATCH(K27,Materials!$A:$A,0))) -> 0 | N27: 0 | O27: P-JACK | P27: 5 | Q27: =IF(O27="",0,P27*INDEX(Plant!$D:$D,MATCH(O27,Plant!$A:$A,0))) -> 750 | R27: =F27+M27+N27+Q27 -> 1801.5669 | S27: =R27*Settings!$B$4*Settings!$B$9 -> 1801.5669 | T27: =S27*(1+Settings!$B$10) -> 2107.8333
A28: DM05 | B28: Strip concrete / clay roof tiles & battens | C28: m2 | D28: G-DEM | E28: 0.25 | F28: =IF(D28="",0,E28*INDEX(Gangs!$D:$D,MATCH(D28,Gangs!$A:$A,0))) -> 43.815287 | M28: =IF(G28="",0,H28*INDEX(Materials!$E:$E,MATCH(G28,Materials!$A:$A,0)))+IF(I28="",0,J28*INDEX(Materials!$E:$E,MATCH(I28,Materials!$A:$A,0)))+IF(K28="",0,L28*INDEX(Materials!$E:$E,MATCH(K28,Materials!$A:$A,0))) -> 0 | N28: 5 | Q28: =IF(O28="",0,P28*INDEX(Plant!$D:$D,MATCH(O28,Plant!$A:$A,0))) -> 0 | R28: =F28+M28+N28+Q28 -> 48.815287 | S28: =R28*Settings!$B$4*Settings!$B$9 -> 48.815287 | T28: =S28*(1+Settings!$B$10) -> 57.113886
A29: DM06 | B29: Strip metal roof sheeting | C29: m2 | D29: G-DEM | E29: 0.15 | F29: =IF(D29="",0,E29*INDEX(Gangs!$D:$D,MATCH(D29,Gangs!$A:$A,0))) -> 26.289172 | M29: =IF(G29="",0,H29*INDEX(Materials!$E:$E,MATCH(G29,Materials!$A:$A,0)))+IF(I29="",0,J29*INDEX(Materials!$E:$E,MATCH(I29,Materials!$A:$A,0)))+IF(K29="",0,L29*INDEX(Materials!$E:$E,MATCH(K29,Materials!$A:$A,0))) -> 0 | N29: 5 | Q29: =IF(O29="",0,P29*INDEX(Plant!$D:$D,MATCH(O29,Plant!$A:$A,0))) -> 0 | R29: =F29+M29+N29+Q29 -> 31.289172 | S29: =R29*Settings!$B$4*Settings!$B$9 -> 31.289172 | T29: =S29*(1+Settings!$B$10) -> 36.608332
A30: DM07 | B30: Remove roof timbers / trusses | C30: m2 | D30: G-DEM | E30: 0.3 | F30: =IF(D30="",0,E30*INDEX(Gangs!$D:$D,MATCH(D30,Gangs!$A:$A,0))) -> 52.578345 | M30: =IF(G30="",0,H30*INDEX(Materials!$E:$E,MATCH(G30,Materials!$A:$A,0)))+IF(I30="",0,J30*INDEX(Materials!$E:$E,MATCH(I30,Materials!$A:$A,0)))+IF(K30="",0,L30*INDEX(Materials!$E:$E,MATCH(K30,Materials!$A:$A,0))) -> 0 | N30: 5 | Q30: =IF(O30="",0,P30*INDEX(Plant!$D:$D,MATCH(O30,Plant!$A:$A,0))) -> 0 | R30: =F30+M30+N30+Q30 -> 57.578345 | S30: =R30*Settings!$B$4*Settings!$B$9 -> 57.578345 | T30: =S30*(1+Settings!$B$10) -> 67.366664
A31: DM08 | B31: Remove ceiling incl brandering & cornice | C31: m2 | D31: G-DEM | E31: 0.2 | F31: =IF(D31="",0,E31*INDEX(Gangs!$D:$D,MATCH(D31,Gangs!$A:$A,0))) -> 35.05223 | M31: =IF(G31="",0,H31*INDEX(Materials!$E:$E,MATCH(G31,Materials!$A:$A,0)))+IF(I31="",0,J31*INDEX(Materials!$E:$E,MATCH(I31,Materials!$A:$A,0)))+IF(K31="",0,L31*INDEX(Materials!$E:$E,MATCH(K31,Materials!$A:$A,0))) -> 0 | N31: 5 | Q31: =IF(O31="",0,P31*INDEX(Plant!$D:$D,MATCH(O31,Plant!$A:$A,0))) -> 0 | R31: =F31+M31+N31+Q31 -> 40.05223 | S31: =R31*Settings!$B$4*Settings!$B$9 -> 40.05223 | T31: =S31*(1+Settings!$B$10) -> 46.861109
A32: DM09 | B32: Hack off wall plaster | C32: m2 | D32: G-DEM | E32: 0.35 | F32: =IF(D32="",0,E32*INDEX(Gangs!$D:$D,MATCH(D32,Gangs!$A:$A,0))) -> 61.341403 | M32: =IF(G32="",0,H32*INDEX(Materials!$E:$E,MATCH(G32,Materials!$A:$A,0)))+IF(I32="",0,J32*INDEX(Materials!$E:$E,MATCH(I32,Materials!$A:$A,0)))+IF(K32="",0,L32*INDEX(Materials!$E:$E,MATCH(K32,Materials!$A:$A,0))) -> 0 | N32: 5 | Q32: =IF(O32="",0,P32*INDEX(Plant!$D:$D,MATCH(O32,Plant!$A:$A,0))) -> 0 | R32: =F32+M32+N32+Q32 -> 66.341403 | S32: =R32*Settings!$B$4*Settings!$B$9 -> 66.341403 | T32: =S32*(1+Settings!$B$10) -> 77.619441
A33: DM10 | B33: Remove floor tiles incl screed | C33: m2 | D33: G-DEM | E33: 0.4 | F33: =IF(D33="",0,E33*INDEX(Gangs!$D:$D,MATCH(D33,Gangs!$A:$A,0))) -> 70.10446 | M33: =IF(G33="",0,H33*INDEX(Materials!$E:$E,MATCH(G33,Materials!$A:$A,0)))+IF(I33="",0,J33*INDEX(Materials!$E:$E,MATCH(I33,Materials!$A:$A,0)))+IF(K33="",0,L33*INDEX(Materials!$E:$E,MATCH(K33,Materials!$A:$A,0))) -> 0 | N33: 5 | Q33: =IF(O33="",0,P33*INDEX(Plant!$D:$D,MATCH(O33,Plant!$A:$A,0))) -> 0 | R33: =F33+M33+N33+Q33 -> 75.10446 | S33: =R33*Settings!$B$4*Settings!$B$9 -> 75.10446 | T33: =S33*(1+Settings!$B$10) -> 87.872218
A34: DM11 | B34: Remove door & frame, make good | C34: no | D34: G-DEM | E34: 1.5 | F34: =IF(D34="",0,E34*INDEX(Gangs!$D:$D,MATCH(D34,Gangs!$A:$A,0))) -> 262.89173 | M34: =IF(G34="",0,H34*INDEX(Materials!$E:$E,MATCH(G34,Materials!$A:$A,0)))+IF(I34="",0,J34*INDEX(Materials!$E:$E,MATCH(I34,Materials!$A:$A,0)))+IF(K34="",0,L34*INDEX(Materials!$E:$E,MATCH(K34,Materials!$A:$A,0))) -> 0 | N34: 60 | Q34: =IF(O34="",0,P34*INDEX(Plant!$D:$D,MATCH(O34,Plant!$A:$A,0))) -> 0 | R34: =F34+M34+N34+Q34 -> 322.89173 | S34: =R34*Settings!$B$4*Settings!$B$9 -> 322.89173 | T34: =S34*(1+Settings!$B$10) -> 377.78332
A35: DM12 | B35: Remove window & frame, make good | C35: no | D35: G-DEM | E35: 2.5 | F35: =IF(D35="",0,E35*INDEX(Gangs!$D:$D,MATCH(D35,Gangs!$A:$A,0))) -> 438.15287 | M35: =IF(G35="",0,H35*INDEX(Materials!$E:$E,MATCH(G35,Materials!$A:$A,0)))+IF(I35="",0,J35*INDEX(Materials!$E:$E,MATCH(I35,Materials!$A:$A,0)))+IF(K35="",0,L35*INDEX(Materials!$E:$E,MATCH(K35,Materials!$A:$A,0))) -> 0 | N35: 90 | Q35: =IF(O35="",0,P35*INDEX(Plant!$D:$D,MATCH(O35,Plant!$A:$A,0))) -> 0 | R35: =F35+M35+N35+Q35 -> 528.15287 | S35: =R35*Settings!$B$4*Settings!$B$9 -> 528.15287 | T35: =S35*(1+Settings!$B$10) -> 617.93886
A36: DM13 | B36: Disconnect & remove sanitary fitting, cap services | C36: no | D36: G-PLB | E36: 1 | F36: =IF(D36="",0,E36*INDEX(Gangs!$D:$D,MATCH(D36,Gangs!$A:$A,0))) -> 226.58405 | M36: =IF(G36="",0,H36*INDEX(Materials!$E:$E,MATCH(G36,Materials!$A:$A,0)))+IF(I36="",0,J36*INDEX(Materials!$E:$E,MATCH(I36,Materials!$A:$A,0)))+IF(K36="",0,L36*INDEX(Materials!$E:$E,MATCH(K36,Materials!$A:$A,0))) -> 0 | N36: 40 | Q36: =IF(O36="",0,P36*INDEX(Plant!$D:$D,MATCH(O36,Plant!$A:$A,0))) -> 0 | R36: =F36+M36+N36+Q36 -> 266.58405 | S36: =R36*Settings!$B$4*Settings!$B$9 -> 266.58405 | T36: =S36*(1+Settings!$B$10) -> 311.90334
A37: DM14 | B37: Form opening <= 1.0 m wide in one-brick wall incl precast lintels, make good | C37: no | D37: G-BRK | E37: 8 | F37: =IF(D37="",0,E37*INDEX(Gangs!$D:$D,MATCH(D37,Gangs!$A:$A,0))) -> 1328.9984 | G37: LINT | H37: 3 | I37: MORT | J37: 0.02 | M37: =IF(G37="",0,H37*INDEX(Materials!$E:$E,MATCH(G37,Materials!$A:$A,0)))+IF(I37="",0,J37*INDEX(Materials!$E:$E,MATCH(I37,Materials!$A:$A,0)))+IF(K37="",0,L37*INDEX(Materials!$E:$E,MATCH(K37,Materials!$A:$A,0))) -> 256.96 | N37: 150 | Q37: =IF(O37="",0,P37*INDEX(Plant!$D:$D,MATCH(O37,Plant!$A:$A,0))) -> 0 | R37: =F37+M37+N37+Q37 -> 1735.9584 | S37: =R37*Settings!$B$4*Settings!$B$9 -> 1735.9584 | T37: =S37*(1+Settings!$B$10) -> 2031.0713
A38: DM15 | B38: Form opening <= 1.0 m wide in half-brick wall incl lintel, make good | C38: no | D38: G-BRK | E38: 5 | F38: =IF(D38="",0,E38*INDEX(Gangs!$D:$D,MATCH(D38,Gangs!$A:$A,0))) -> 830.624 | G38: LINT | H38: 1.5 | I38: MORT | J38: 0.01 | M38: =IF(G38="",0,H38*INDEX(Materials!$E:$E,MATCH(G38,Materials!$A:$A,0)))+IF(I38="",0,J38*INDEX(Materials!$E:$E,MATCH(I38,Materials!$A:$A,0)))+IF(K38="",0,L38*INDEX(Materials!$E:$E,MATCH(K38,Materials!$A:$A,0))) -> 128.48 | N38: 100 | Q38: =IF(O38="",0,P38*INDEX(Plant!$D:$D,MATCH(O38,Plant!$A:$A,0))) -> 0 | R38: =F38+M38+N38+Q38 -> 1059.104 | S38: =R38*Settings!$B$4*Settings!$B$9 -> 1059.104 | T38: =S38*(1+Settings!$B$10) -> 1239.1517
A39: DM16 | B39: Needle & prop loadbearing wall for new opening (props hire allowance) | C39: no | D39: G-BRK | E39: 6 | F39: =IF(D39="",0,E39*INDEX(Gangs!$D:$D,MATCH(D39,Gangs!$A:$A,0))) -> 996.7488 | M39: =IF(G39="",0,H39*INDEX(Materials!$E:$E,MATCH(G39,Materials!$A:$A,0)))+IF(I39="",0,J39*INDEX(Materials!$E:$E,MATCH(I39,Materials!$A:$A,0)))+IF(K39="",0,L39*INDEX(Materials!$E:$E,MATCH(K39,Materials!$A:$A,0))) -> 0 | N39: 850 | Q39: =IF(O39="",0,P39*INDEX(Plant!$D:$D,MATCH(O39,Plant!$A:$A,0))) -> 0 | R39: =F39+M39+N39+Q39 -> 1846.7488 | S39: =R39*Settings!$B$4*Settings!$B$9 -> 1846.7488 | T39: =S39*(1+Settings!$B$10) -> 2160.6961
A40: DM17 | B40: Load & cart rubble to licensed tip incl tip fees | C40: m3 | D40: G-LAB | E40: 0.5 | F40: =IF(D40="",0,E40*INDEX(Gangs!$D:$D,MATCH(D40,Gangs!$A:$A,0))) -> 26.554525 | M40: =IF(G40="",0,H40*INDEX(Materials!$E:$E,MATCH(G40,Materials!$A:$A,0)))+IF(I40="",0,J40*INDEX(Materials!$E:$E,MATCH(I40,Materials!$A:$A,0)))+IF(K40="",0,L40*INDEX(Materials!$E:$E,MATCH(K40,Materials!$A:$A,0))) -> 0 | N40: 0 | O40: P-CARTRUB | P40: 1 | Q40: =IF(O40="",0,P40*INDEX(Plant!$D:$D,MATCH(O40,Plant!$A:$A,0))) -> 380 | R40: =F40+M40+N40+Q40 -> 406.55453 | S40: =R40*Settings!$B$4*Settings!$B$9 -> 406.55453 | T40: =S40*(1+Settings!$B$10) -> 475.66879
A41: EARTHWORKS
A42: EW01 | B42: Clear site & remove topsoil 150 mm | C42: m2 | D42: G-LAB | E42: 0.02 | F42: =IF(D42="",0,E42*INDEX(Gangs!$D:$D,MATCH(D42,Gangs!$A:$A,0))) -> 1.062181 | M42: =IF(G42="",0,H42*INDEX(Materials!$E:$E,MATCH(G42,Materials!$A:$A,0)))+IF(I42="",0,J42*INDEX(Materials!$E:$E,MATCH(I42,Materials!$A:$A,0)))+IF(K42="",0,L42*INDEX(Materials!$E:$E,MATCH(K42,Materials!$A:$A,0))) -> 0 | N42: 0 | O42: P-TLB | P42: 0.012 | Q42: =IF(O42="",0,P42*INDEX(Plant!$D:$D,MATCH(O42,Plant!$A:$A,0))) -> 6.24 | R42: =F42+M42+N42+Q42 -> 7.302181 | S42: =R42*Settings!$B$4*Settings!$B$9 -> 7.302181 | T42: =S42*(1+Settings!$B$10) -> 8.5435518
A43: EW02 | B43: Excavate trenches <= 1.5 m deep by machine, soft material | C43: m3 | D43: G-LAB | E43: 0.25 | F43: =IF(D43="",0,E43*INDEX(Gangs!$D:$D,MATCH(D43,Gangs!$A:$A,0))) -> 13.277263 | M43: =IF(G43="",0,H43*INDEX(Materials!$E:$E,MATCH(G43,Materials!$A:$A,0)))+IF(I43="",0,J43*INDEX(Materials!$E:$E,MATCH(I43,Materials!$A:$A,0)))+IF(K43="",0,L43*INDEX(Materials!$E:$E,MATCH(K43,Materials!$A:$A,0))) -> 0 | N43: 0 | O43: P-TLB | P43: 0.16 | Q43: =IF(O43="",0,P43*INDEX(Plant!$D:$D,MATCH(O43,Plant!$A:$A,0))) -> 83.2 | R43: =F43+M43+N43+Q43 -> 96.477262 | S43: =R43*Settings!$B$4*Settings!$B$9 -> 96.477262 | T43: =S43*(1+Settings!$B$10) -> 112.8784
A44: EW03 | B44: Excavate trenches <= 1.5 m deep by hand, soft material | C44: m3 | D44: G-LAB | E44: 3.2 | F44: =IF(D44="",0,E44*INDEX(Gangs!$D:$D,MATCH(D44,Gangs!$A:$A,0))) -> 169.94896 | M44: =IF(G44="",0,H44*INDEX(Materials!$E:$E,MATCH(G44,Materials!$A:$A,0)))+IF(I44="",0,J44*INDEX(Materials!$E:$E,MATCH(I44,Materials!$A:$A,0)))+IF(K44="",0,L44*INDEX(Materials!$E:$E,MATCH(K44,Materials!$A:$A,0))) -> 0 | N44: 0 | Q44: =IF(O44="",0,P44*INDEX(Plant!$D:$D,MATCH(O44,Plant!$A:$A,0))) -> 0 | R44: =F44+M44+N44+Q44 -> 169.94896 | S44: =R44*Settings!$B$4*Settings!$B$9 -> 169.94896 | T44: =S44*(1+Settings!$B$10) -> 198.84028
A45: EW04 | B45: Extra over for intermediate excavation | C45: m3 | D45: G-LAB | E45: 1 | F45: =IF(D45="",0,E45*INDEX(Gangs!$D:$D,MATCH(D45,Gangs!$A:$A,0))) -> 53.10905 | M45: =IF(G45="",0,H45*INDEX(Materials!$E:$E,MATCH(G45,Materials!$A:$A,0)))+IF(I45="",0,J45*INDEX(Materials!$E:$E,MATCH(I45,Materials!$A:$A,0)))+IF(K45="",0,L45*INDEX(Materials!$E:$E,MATCH(K45,Materials!$A:$A,0))) -> 0 | N45: 0 | O45: P-JACK | P45: 1.5 | Q45: =IF(O45="",0,P45*INDEX(Plant!$D:$D,MATCH(O45,Plant!$A:$A,0))) -> 225 | R45: =F45+M45+N45+Q45 -> 278.10905 | S45: =R45*Settings!$B$4*Settings!$B$9 -> 278.10905 | T45: =S45*(1+Settings!$B$10) -> 325.38759
A46: EW05 | B46: Extra over for hard rock excavation (breaker) | C46: m3 | D46: G-LAB | E46: 2 | F46: =IF(D46="",0,E46*INDEX(Gangs!$D:$D,MATCH(D46,Gangs!$A:$A,0))) -> 106.2181 | M46: =IF(G46="",0,H46*INDEX(Materials!$E:$E,MATCH(G46,Materials!$A:$A,0)))+IF(I46="",0,J46*INDEX(Materials!$E:$E,MATCH(I46,Materials!$A:$A,0)))+IF(K46="",0,L46*INDEX(Materials!$E:$E,MATCH(K46,Materials!$A:$A,0))) -> 0 | N46: 520 | O46: P-JACK | P46: 3 | Q46: =IF(O46="",0,P46*INDEX(Plant!$D:$D,MATCH(O46,Plant!$A:$A,0))) -> 450 | R46: =F46+M46+N46+Q46 -> 1076.2181 | S46: =R46*Settings!$B$4*Settings!$B$9 -> 1076.2181 | T46: =S46*(1+Settings!$B$10) -> 1259.1752
A47: EW06 | B47: Bulk excavation by machine <= 2 m deep | C47: m3 | D47: G-LAB | E47: 0.05 | F47: =IF(D47="",0,E47*INDEX(Gangs!$D:$D,MATCH(D47,Gangs!$A:$A,0))) -> 2.6554525 | M47: =IF(G47="",0,H47*INDEX(Materials!$E:$E,MATCH(G47,Materials!$A:$A,0)))+IF(I47="",0,J47*INDEX(Materials!$E:$E,MATCH(I47,Materials!$A:$A,0)))+IF(K47="",0,L47*INDEX(Materials!$E:$E,MATCH(K47,Materials!$A:$A,0))) -> 0 | N47: 0 | O47: P-EXC20 | P47: 0.06 | Q47: =IF(O47="",0,P47*INDEX(Plant!$D:$D,MATCH(O47,Plant!$A:$A,0))) -> 63 | R47: =F47+M47+N47+Q47 -> 65.655452 | S47: =R47*Settings!$B$4*Settings!$B$9 -> 65.655452 | T47: =S47*(1+Settings!$B$10) -> 76.816879
A48: EW07 | B48: Excavate bases / pits by machine | C48: m3 | D48: G-LAB | E48: 0.3 | F48: =IF(D48="",0,E48*INDEX(Gangs!$D:$D,MATCH(D48,Gangs!$A:$A,0))) -> 15.932715 | M48: =IF(G48="",0,H48*INDEX(Materials!$E:$E,MATCH(G48,Materials!$A:$A,0)))+IF(I48="",0,J48*INDEX(Materials!$E:$E,MATCH(I48,Materials!$A:$A,0)))+IF(K48="",0,L48*INDEX(Materials!$E:$E,MATCH(K48,Materials!$A:$A,0))) -> 0 | N48: 0 | O48: P-TLB | P48: 0.2 | Q48: =IF(O48="",0,P48*INDEX(Plant!$D:$D,MATCH(O48,Plant!$A:$A,0))) -> 104 | R48: =F48+M48+N48+Q48 -> 119.93272 | S48: =R48*Settings!$B$4*Settings!$B$9 -> 119.93272 | T48: =S48*(1+Settings!$B$10) -> 140.32128
A49: EW08 | B49: Earthwork support to trench sides <= 1.5 m | C49: m2 | D49: G-LAB | E49: 0.3 | F49: =IF(D49="",0,E49*INDEX(Gangs!$D:$D,MATCH(D49,Gangs!$A:$A,0))) -> 15.932715 | M49: =IF(G49="",0,H49*INDEX(Materials!$E:$E,MATCH(G49,Materials!$A:$A,0)))+IF(I49="",0,J49*INDEX(Materials!$E:$E,MATCH(I49,Materials!$A:$A,0)))+IF(K49="",0,L49*INDEX(Materials!$E:$E,MATCH(K49,Materials!$A:$A,0))) -> 0 | N49: 45 | Q49: =IF(O49="",0,P49*INDEX(Plant!$D:$D,MATCH(O49,Plant!$A:$A,0))) -> 0 | R49: =F49+M49+N49+Q49 -> 60.932715 | S49: =R49*Settings!$B$4*Settings!$B$9 -> 60.932715 | T49: =S49*(1+Settings!$B$10) -> 71.291277
A50: EW09 | B50: Keep excavations free of water | C50: day | D50: G-LAB | E50: 2 | F50: =IF(D50="",0,E50*INDEX(Gangs!$D:$D,MATCH(D50,Gangs!$A:$A,0))) -> 106.2181 | M50: =IF(G50="",0,H50*INDEX(Materials!$E:$E,MATCH(G50,Materials!$A:$A,0)))+IF(I50="",0,J50*INDEX(Materials!$E:$E,MATCH(I50,Materials!$A:$A,0)))+IF(K50="",0,L50*INDEX(Materials!$E:$E,MATCH(K50,Materials!$A:$A,0))) -> 0 | N50: 0 | O50: P-PUMP | P50: 1 | Q50: =IF(O50="",0,P50*INDEX(Plant!$D:$D,MATCH(O50,Plant!$A:$A,0))) -> 450 | R50: =F50+M50+N50+Q50 -> 556.2181 | S50: =R50*Settings!$B$4*Settings!$B$9 -> 556.2181 | T50: =S50*(1+Settings!$B$10) -> 650.77518
A51: EW10 | B51: Backfill with excavated material, compacted in 150 mm layers | C51: m3 | D51: G-LAB | E51: 1.2 | F51: =IF(D51="",0,E51*INDEX(Gangs!$D:$D,MATCH(D51,Gangs!$A:$A,0))) -> 63.73086 | M51: =IF(G51="",0,H51*INDEX(Materials!$E:$E,MATCH(G51,Materials!$A:$A,0)))+IF(I51="",0,J51*INDEX(Materials!$E:$E,MATCH(I51,Materials!$A:$A,0)))+IF(K51="",0,L51*INDEX(Materials!$E:$E,MATCH(K51,Materials!$A:$A,0))) -> 0 | N51: 0 | O51: P-PLATE | P51: 0.067 | Q51: =IF(O51="",0,P51*INDEX(Plant!$D:$D,MATCH(O51,Plant!$A:$A,0))) -> 25.46 | R51: =F51+M51+N51+Q51 -> 89.19086 | S51: =R51*Settings!$B$4*Settings!$B$9 -> 89.19086 | T51: =S51*(1+Settings!$B$10) -> 104.35331
A52: EW11 | B52: Imported G5 fill under floors, compacted to 93% MOD AASHTO | C52: m3 | D52: G-LAB | E52: 0.8 | F52: =IF(D52="",0,E52*INDEX(Gangs!$D:$D,MATCH(D52,Gangs!$A:$A,0))) -> 42.48724 | G52: G5 | H52: 1.3 | M52: =IF(G52="",0,H52*INDEX(Materials!$E:$E,MATCH(G52,Materials!$A:$A,0)))+IF(I52="",0,J52*INDEX(Materials!$E:$E,MATCH(I52,Materials!$A:$A,0)))+IF(K52="",0,L52*INDEX(Materials!$E:$E,MATCH(K52,Materials!$A:$A,0))) -> 390 | N52: 0 | O52: P-PLATE | P52: 0.08 | Q52: =IF(O52="",0,P52*INDEX(Plant!$D:$D,MATCH(O52,Plant!$A:$A,0))) -> 30.4 | R52: =F52+M52+N52+Q52 -> 462.88724 | S52: =R52*Settings!$B$4*Settings!$B$9 -> 462.88724 | T52: =S52*(1+Settings!$B$10) -> 541.57807
A53: EW12 | B53: Load & cart surplus excavated material <= 10 km | C53: m3 | D53: G-LAB | E53: 0.1 | F53: =IF(D53="",0,E53*INDEX(Gangs!$D:$D,MATCH(D53,Gangs!$A:$A,0))) -> 5.310905 | M53: =IF(G53="",0,H53*INDEX(Materials!$E:$E,MATCH(G53,Materials!$A:$A,0)))+IF(I53="",0,J53*INDEX(Materials!$E:$E,MATCH(I53,Materials!$A:$A,0)))+IF(K53="",0,L53*INDEX(Materials!$E:$E,MATCH(K53,Materials!$A:$A,0))) -> 0 | N53: 0 | O53: P-CARTSOIL | P53: 1.25 | Q53: =IF(O53="",0,P53*INDEX(Plant!$D:$D,MATCH(O53,Plant!$A:$A,0))) -> 212.5 | R53: =F53+M53+N53+Q53 -> 217.8109 | S53: =R53*Settings!$B$4*Settings!$B$9 -> 217.8109 | T53: =S53*(1+Settings!$B$10) -> 254.83876
A54: EW13 | B54: Soil poisoning (termite treatment) by registered PCO | C54: m2 | F54: =IF(D54="",0,E54*INDEX(Gangs!$D:$D,MATCH(D54,Gangs!$A:$A,0))) -> 0 | M54: =IF(G54="",0,H54*INDEX(Materials!$E:$E,MATCH(G54,Materials!$A:$A,0)))+IF(I54="",0,J54*INDEX(Materials!$E:$E,MATCH(I54,Materials!$A:$A,0)))+IF(K54="",0,L54*INDEX(Materials!$E:$E,MATCH(K54,Materials!$A:$A,0))) -> 0 | N54: 22 | Q54: =IF(O54="",0,P54*INDEX(Plant!$D:$D,MATCH(O54,Plant!$A:$A,0))) -> 0 | R54: =F54+M54+N54+Q54 -> 22 | S54: =R54*Settings!$B$4*Settings!$B$9 -> 22 | T54: =S54*(1+Settings!$B$10) -> 25.74
A55: EW14 | B55: Compact bottoms of excavations | C55: m2 | D55: G-LAB | E55: 0.08 | F55: =IF(D55="",0,E55*INDEX(Gangs!$D:$D,MATCH(D55,Gangs!$A:$A,0))) -> 4.248724 | M55: =IF(G55="",0,H55*INDEX(Materials!$E:$E,MATCH(G55,Materials!$A:$A,0)))+IF(I55="",0,J55*INDEX(Materials!$E:$E,MATCH(I55,Materials!$A:$A,0)))+IF(K55="",0,L55*INDEX(Materials!$E:$E,MATCH(K55,Materials!$A:$A,0))) -> 0 | N55: 0 | O55: P-PLATE | P55: 0.01 | Q55: =IF(O55="",0,P55*INDEX(Plant!$D:$D,MATCH(O55,Plant!$A:$A,0))) -> 3.8 | R55: =F55+M55+N55+Q55 -> 8.048724 | S55: =R55*Settings!$B$4*Settings!$B$9 -> 8.048724 | T55: =S55*(1+Settings!$B$10) -> 9.4170071
A56: EW15 | B56: Level & compact ground under surface beds | C56: m2 | D56: G-LAB | E56: 0.1 | F56: =IF(D56="",0,E56*INDEX(Gangs!$D:$D,MATCH(D56,Gangs!$A:$A,0))) -> 5.310905 | M56: =IF(G56="",0,H56*INDEX(Materials!$E:$E,MATCH(G56,Materials!$A:$A,0)))+IF(I56="",0,J56*INDEX(Materials!$E:$E,MATCH(I56,Materials!$A:$A,0)))+IF(K56="",0,L56*INDEX(Materials!$E:$E,MATCH(K56,Materials!$A:$A,0))) -> 0 | N56: 0 | O56: P-PLATE | P56: 0.01 | Q56: =IF(O56="",0,P56*INDEX(Plant!$D:$D,MATCH(O56,Plant!$A:$A,0))) -> 3.8 | R56: =F56+M56+N56+Q56 -> 9.110905 | S56: =R56*Settings!$B$4*Settings!$B$9 -> 9.110905 | T56: =S56*(1+Settings!$B$10) -> 10.659759
A57: EW16 | B57: Spread & level topsoil 150 mm | C57: m2 | D57: G-LAB | E57: 0.15 | F57: =IF(D57="",0,E57*INDEX(Gangs!$D:$D,MATCH(D57,Gangs!$A:$A,0))) -> 7.9663575 | M57: =IF(G57="",0,H57*INDEX(Materials!$E:$E,MATCH(G57,Materials!$A:$A,0)))+IF(I57="",0,J57*INDEX(Materials!$E:$E,MATCH(I57,Materials!$A:$A,0)))+IF(K57="",0,L57*INDEX(Materials!$E:$E,MATCH(K57,Materials!$A:$A,0))) -> 0 | N57: 0 | Q57: =IF(O57="",0,P57*INDEX(Plant!$D:$D,MATCH(O57,Plant!$A:$A,0))) -> 0 | R57: =F57+M57+N57+Q57 -> 7.9663575 | S57: =R57*Settings!$B$4*Settings!$B$9 -> 7.9663575 | T57: =S57*(1+Settings!$B$10) -> 9.3206383
A58: CONCRETE, FORMWORK & REINFORCEMENT
A59: CN01 | B59: Blinding 15 MPa, 50 mm under footings | C59: m2 | D59: G-CON | E59: 0.05 | F59: =IF(D59="",0,E59*INDEX(Gangs!$D:$D,MATCH(D59,Gangs!$A:$A,0))) -> 14.413845 | G59: RM15 | H59: 0.053 | M59: =IF(G59="",0,H59*INDEX(Materials!$E:$E,MATCH(G59,Materials!$A:$A,0)))+IF(I59="",0,J59*INDEX(Materials!$E:$E,MATCH(I59,Materials!$A:$A,0)))+IF(K59="",0,L59*INDEX(Materials!$E:$E,MATCH(K59,Materials!$A:$A,0))) -> 80.56 | N59: 0 | Q59: =IF(O59="",0,P59*INDEX(Plant!$D:$D,MATCH(O59,Plant!$A:$A,0))) -> 0 | R59: =F59+M59+N59+Q59 -> 94.973845 | S59: =R59*Settings!$B$4*Settings!$B$9 -> 94.973845 | T59: =S59*(1+Settings!$B$10) -> 111.1194
A60: CN02 | B60: Readymix 25 MPa in strip footings | C60: m3 | D60: G-CON | E60: 0.8 | F60: =IF(D60="",0,E60*INDEX(Gangs!$D:$D,MATCH(D60,Gangs!$A:$A,0))) -> 230.62152 | G60: RM25 | H60: 1.05 | M60: =IF(G60="",0,H60*INDEX(Materials!$E:$E,MATCH(G60,Materials!$A:$A,0)))+IF(I60="",0,J60*INDEX(Materials!$E:$E,MATCH(I60,Materials!$A:$A,0)))+IF(K60="",0,L60*INDEX(Materials!$E:$E,MATCH(K60,Materials!$A:$A,0))) -> 1774.5 | N60: 0 | O60: P-POKER | P60: 0.05 | Q60: =IF(O60="",0,P60*INDEX(Plant!$D:$D,MATCH(O60,Plant!$A:$A,0))) -> 16 | R60: =F60+M60+N60+Q60 -> 2021.1215 | S60: =R60*Settings!$B$4*Settings!$B$9 -> 2021.1215 | T60: =S60*(1+Settings!$B$10) -> 2364.7122
A61: CN03 | B61: Readymix 25 MPa in pad / column bases | C61: m3 | D61: G-CON | E61: 1 | F61: =IF(D61="",0,E61*INDEX(Gangs!$D:$D,MATCH(D61,Gangs!$A:$A,0))) -> 288.2769 | G61: RM25 | H61: 1.05 | M61: =IF(G61="",0,H61*INDEX(Materials!$E:$E,MATCH(G61,Materials!$A:$A,0)))+IF(I61="",0,J61*INDEX(Materials!$E:$E,MATCH(I61,Materials!$A:$A,0)))+IF(K61="",0,L61*INDEX(Materials!$E:$E,MATCH(K61,Materials!$A:$A,0))) -> 1774.5 | N61: 0 | O61: P-POKER | P61: 0.06 | Q61: =IF(O61="",0,P61*INDEX(Plant!$D:$D,MATCH(O61,Plant!$A:$A,0))) -> 19.2 | R61: =F61+M61+N61+Q61 -> 2081.9769 | S61: =R61*Settings!$B$4*Settings!$B$9 -> 2081.9769 | T61: =S61*(1+Settings!$B$10) -> 2435.913
A62: CN04 | B62: Readymix 25 MPa in surface beds <= 150 mm | C62: m3 | D62: G-CON | E62: 1.3 | F62: =IF(D62="",0,E62*INDEX(Gangs!$D:$D,MATCH(D62,Gangs!$A:$A,0))) -> 374.75997 | G62: RM25 | H62: 1.05 | M62: =IF(G62="",0,H62*INDEX(Materials!$E:$E,MATCH(G62,Materials!$A:$A,0)))+IF(I62="",0,J62*INDEX(Materials!$E:$E,MATCH(I62,Materials!$A:$A,0)))+IF(K62="",0,L62*INDEX(Materials!$E:$E,MATCH(K62,Materials!$A:$A,0))) -> 1774.5 | N62: 0 | O62: P-POKER | P62: 0.05 | Q62: =IF(O62="",0,P62*INDEX(Plant!$D:$D,MATCH(O62,Plant!$A:$A,0))) -> 16 | R62: =F62+M62+N62+Q62 -> 2165.26 | S62: =R62*Settings!$B$4*Settings!$B$9 -> 2165.26 | T62: =S62*(1+Settings!$B$10) -> 2533.3542
A63: CN05 | B63: Readymix 25 MPa in ground beams | C63: m3 | D63: G-CON | E63: 1.1 | F63: =IF(D63="",0,E63*INDEX(Gangs!$D:$D,MATCH(D63,Gangs!$A:$A,0))) -> 317.10459 | G63: RM25 | H63: 1.05 | M63: =IF(G63="",0,H63*INDEX(Materials!$E:$E,MATCH(G63,Materials!$A:$A,0)))+IF(I63="",0,J63*INDEX(Materials!$E:$E,MATCH(I63,Materials!$A:$A,0)))+IF(K63="",0,L63*INDEX(Materials!$E:$E,MATCH(K63,Materials!$A:$A,0))) -> 1774.5 | N63: 0 | O63: P-POKER | P63: 0.06 | Q63: =IF(O63="",0,P63*INDEX(Plant!$D:$D,MATCH(O63,Plant!$A:$A,0))) -> 19.2 | R63: =F63+M63+N63+Q63 -> 2110.8046 | S63: =R63*Settings!$B$4*Settings!$B$9 -> 2110.8046 | T63: =S63*(1+Settings!$B$10) -> 2469.6414
A64: CN06 | B64: Readymix 30 MPa in suspended slabs, pumped | C64: m3 | D64: G-CON | E64: 1.4 | F64: =IF(D64="",0,E64*INDEX(Gangs!$D:$D,MATCH(D64,Gangs!$A:$A,0))) -> 403.58766 | G64: RM30 | H64: 1.05 | M64: =IF(G64="",0,H64*INDEX(Materials!$E:$E,MATCH(G64,Materials!$A:$A,0)))+IF(I64="",0,J64*INDEX(Materials!$E:$E,MATCH(I64,Materials!$A:$A,0)))+IF(K64="",0,L64*INDEX(Materials!$E:$E,MATCH(K64,Materials!$A:$A,0))) -> 1890 | N64: 0 | O64: P-CPUMP | P64: 1 | Q64: =IF(O64="",0,P64*INDEX(Plant!$D:$D,MATCH(O64,Plant!$A:$A,0))) -> 170 | R64: =F64+M64+N64+Q64 -> 2463.5877 | S64: =R64*Settings!$B$4*Settings!$B$9 -> 2463.5877 | T64: =S64*(1+Settings!$B$10) -> 2882.3976
A65: CN07 | B65: Readymix 30 MPa in beams, pumped | C65: m3 | D65: G-CON | E65: 1.8 | F65: =IF(D65="",0,E65*INDEX(Gangs!$D:$D,MATCH(D65,Gangs!$A:$A,0))) -> 518.89842 | G65: RM30 | H65: 1.05 | M65: =IF(G65="",0,H65*INDEX(Materials!$E:$E,MATCH(G65,Materials!$A:$A,0)))+IF(I65="",0,J65*INDEX(Materials!$E:$E,MATCH(I65,Materials!$A:$A,0)))+IF(K65="",0,L65*INDEX(Materials!$E:$E,MATCH(K65,Materials!$A:$A,0))) -> 1890 | N65: 0 | O65: P-CPUMP | P65: 1 | Q65: =IF(O65="",0,P65*INDEX(Plant!$D:$D,MATCH(O65,Plant!$A:$A,0))) -> 170 | R65: =F65+M65+N65+Q65 -> 2578.8984 | S65: =R65*Settings!$B$4*Settings!$B$9 -> 2578.8984 | T65: =S65*(1+Settings!$B$10) -> 3017.3112
A66: CN08 | B66: Readymix 30 MPa in columns, pumped | C66: m3 | D66: G-CON | E66: 2.2 | F66: =IF(D66="",0,E66*INDEX(Gangs!$D:$D,MATCH(D66,Gangs!$A:$A,0))) -> 634.20918 | G66: RM30 | H66: 1.05 | M66: =IF(G66="",0,H66*INDEX(Materials!$E:$E,MATCH(G66,Materials!$A:$A,0)))+IF(I66="",0,J66*INDEX(Materials!$E:$E,MATCH(I66,Materials!$A:$A,0)))+IF(K66="",0,L66*INDEX(Materials!$E:$E,MATCH(K66,Materials!$A:$A,0))) -> 1890 | N66: 0 | O66: P-CPUMP | P66: 1 | Q66: =IF(O66="",0,P66*INDEX(Plant!$D:$D,MATCH(O66,Plant!$A:$A,0))) -> 170 | R66: =F66+M66+N66+Q66 -> 2694.2092 | S66: =R66*Settings!$B$4*Settings!$B$9 -> 2694.2092 | T66: =S66*(1+Settings!$B$10) -> 3152.2247
A67: CN09 | B67: Site-mixed 25 MPa in footings (no readymix access) | C67: m3 | D67: G-CON | E67: 2.5 | F67: =IF(D67="",0,E67*INDEX(Gangs!$D:$D,MATCH(D67,Gangs!$A:$A,0))) -> 720.69225 | G67: CSITE | H67: 1.05 | M67: =IF(G67="",0,H67*INDEX(Materials!$E:$E,MATCH(G67,Materials!$A:$A,0)))+IF(I67="",0,J67*INDEX(Materials!$E:$E,MATCH(I67,Materials!$A:$A,0)))+IF(K67="",0,L67*INDEX(Materials!$E:$E,MATCH(K67,Materials!$A:$A,0))) -> 1488.9 | N67: 0 | O67: P-MIXER | P67: 0.15 | Q67: =IF(O67="",0,P67*INDEX(Plant!$D:$D,MATCH(O67,Plant!$A:$A,0))) -> 45 | R67: =F67+M67+N67+Q67 -> 2254.5923 | S67: =R67*Settings!$B$4*Settings!$B$9 -> 2254.5923 | T67: =S67*(1+Settings!$B$10) -> 2637.8729
A68: CN10 | B68: Site-mixed 25 MPa in surface beds | C68: m3 | D68: G-CON | E68: 2.8 | F68: =IF(D68="",0,E68*INDEX(Gangs!$D:$D,MATCH(D68,Gangs!$A:$A,0))) -> 807.17532 | G68: CSITE | H68: 1.05 | M68: =IF(G68="",0,H68*INDEX(Materials!$E:$E,MATCH(G68,Materials!$A:$A,0)))+IF(I68="",0,J68*INDEX(Materials!$E:$E,MATCH(I68,Materials!$A:$A,0)))+IF(K68="",0,L68*INDEX(Materials!$E:$E,MATCH(K68,Materials!$A:$A,0))) -> 1488.9 | N68: 0 | O68: P-MIXER | P68: 0.15 | Q68: =IF(O68="",0,P68*INDEX(Plant!$D:$D,MATCH(O68,Plant!$A:$A,0))) -> 45 | R68: =F68+M68+N68+Q68 -> 2341.0753 | S68: =R68*Settings!$B$4*Settings!$B$9 -> 2341.0753 | T68: =S68*(1+Settings!$B$10) -> 2739.0581
A69: CN11 | B69: Surface bed 100 mm 25 MPa readymix incl wood-float finish | C69: m2 | D69: G-CON | E69: 0.2 | F69: =IF(D69="",0,E69*INDEX(Gangs!$D:$D,MATCH(D69,Gangs!$A:$A,0))) -> 57.65538 | G69: RM25 | H69: 0.105 | M69: =IF(G69="",0,H69*INDEX(Materials!$E:$E,MATCH(G69,Materials!$A:$A,0)))+IF(I69="",0,J69*INDEX(Materials!$E:$E,MATCH(I69,Materials!$A:$A,0)))+IF(K69="",0,L69*INDEX(Materials!$E:$E,MATCH(K69,Materials!$A:$A,0))) -> 177.45 | N69: 4 | Q69: =IF(O69="",0,P69*INDEX(Plant!$D:$D,MATCH(O69,Plant!$A:$A,0))) -> 0 | R69: =F69+M69+N69+Q69 -> 239.10538 | S69: =R69*Settings!$B$4*Settings!$B$9 -> 239.10538 | T69: =S69*(1+Settings!$B$10) -> 279.75329
A70: CN12 | B70: Steel-trowel finish to concrete | C70: m2 | D70: G-SCR | E70: 0.12 | F70: =IF(D70="",0,E70*INDEX(Gangs!$D:$D,MATCH(D70,Gangs!$A:$A,0))) -> 19.934976 | M70: =IF(G70="",0,H70*INDEX(Materials!$E:$E,MATCH(G70,Materials!$A:$A,0)))+IF(I70="",0,J70*INDEX(Materials!$E:$E,MATCH(I70,Materials!$A:$A,0)))+IF(K70="",0,L70*INDEX(Materials!$E:$E,MATCH(K70,Materials!$A:$A,0))) -> 0 | N70: 0 | Q70: =IF(O70="",0,P70*INDEX(Plant!$D:$D,MATCH(O70,Plant!$A:$A,0))) -> 0 | R70: =F70+M70+N70+Q70 -> 19.934976 | S70: =R70*Settings!$B$4*Settings!$B$9 -> 19.934976 | T70: =S70*(1+Settings!$B$10) -> 23.323922
A71: CN13 | B71: Power-float finish to concrete | C71: m2 | D71: G-SCR | E71: 0.06 | F71: =IF(D71="",0,E71*INDEX(Gangs!$D:$D,MATCH(D71,Gangs!$A:$A,0))) -> 9.967488 | M71: =IF(G71="",0,H71*INDEX(Materials!$E:$E,MATCH(G71,Materials!$A:$A,0)))+IF(I71="",0,J71*INDEX(Materials!$E:$E,MATCH(I71,Materials!$A:$A,0)))+IF(K71="",0,L71*INDEX(Materials!$E:$E,MATCH(K71,Materials!$A:$A,0))) -> 0 | N71: 0 | O71: P-FLOAT | P71: 0.007 | Q71: =IF(O71="",0,P71*INDEX(Plant!$D:$D,MATCH(O71,Plant!$A:$A,0))) -> 4.2 | R71: =F71+M71+N71+Q71 -> 14.167488 | S71: =R71*Settings!$B$4*Settings!$B$9 -> 14.167488 | T71: =S71*(1+Settings!$B$10) -> 16.575961
A72: CN14 | B72: 250 micron DPM under surface beds, lapped & taped | C72: m2 | D72: G-LAB | E72: 0.03 | F72: =IF(D72="",0,E72*INDEX(Gangs!$D:$D,MATCH(D72,Gangs!$A:$A,0))) -> 1.5932715 | G72: DPM250 | H72: 1.15 | M72: =IF(G72="",0,H72*INDEX(Materials!$E:$E,MATCH(G72,Materials!$A:$A,0)))+IF(I72="",0,J72*INDEX(Materials!$E:$E,MATCH(I72,Materials!$A:$A,0)))+IF(K72="",0,L72*INDEX(Materials!$E:$E,MATCH(K72,Materials!$A:$A,0))) -> 8.625 | N72: 1 | Q72: =IF(O72="",0,P72*INDEX(Plant!$D:$D,MATCH(O72,Plant!$A:$A,0))) -> 0 | R72: =F72+M72+N72+Q72 -> 11.218272 | S72: =R72*Settings!$B$4*Settings!$B$9 -> 11.218272 | T72: =S72*(1+Settings!$B$10) -> 13.125378
A73: CN15 | B73: Rough formwork to sides of footings / bases | C73: m2 | D73: G-SHT | E73: 0.9 | F73: =IF(D73="",0,E73*INDEX(Gangs!$D:$D,MATCH(D73,Gangs!$A:$A,0))) -> 149.51232 | G73: FWMAT | H73: 0.6 | M73: =IF(G73="",0,H73*INDEX(Materials!$E:$E,MATCH(G73,Materials!$A:$A,0)))+IF(I73="",0,J73*INDEX(Materials!$E:$E,MATCH(I73,Materials!$A:$A,0)))+IF(K73="",0,L73*INDEX(Materials!$E:$E,MATCH(K73,Materials!$A:$A,0))) -> 52.8 | N73: 0 | Q73: =IF(O73="",0,P73*INDEX(Plant!$D:$D,MATCH(O73,Plant!$A:$A,0))) -> 0 | R73: =F73+M73+N73+Q73 -> 202.31232 | S73: =R73*Settings!$B$4*Settings!$B$9 -> 202.31232 | T73: =S73*(1+Settings!$B$10) -> 236.70541
A74: CN16 | B74: Smooth formwork to sides & soffits of beams | C74: m2 | D74: G-SHT | E74: 1.5 | F74: =IF(D74="",0,E74*INDEX(Gangs!$D:$D,MATCH(D74,Gangs!$A:$A,0))) -> 249.1872 | G74: FWMAT | H74: 1 | M74: =IF(G74="",0,H74*INDEX(Materials!$E:$E,MATCH(G74,Materials!$A:$A,0)))+IF(I74="",0,J74*INDEX(Materials!$E:$E,MATCH(I74,Materials!$A:$A,0)))+IF(K74="",0,L74*INDEX(Materials!$E:$E,MATCH(K74,Materials!$A:$A,0))) -> 88 | N74: 20 | Q74: =IF(O74="",0,P74*INDEX(Plant!$D:$D,MATCH(O74,Plant!$A:$A,0))) -> 0 | R74: =F74+M74+N74+Q74 -> 357.1872 | S74: =R74*Settings!$B$4*Settings!$B$9 -> 357.1872 | T74: =S74*(1+Settings!$B$10) -> 417.90902
A75: CN17 | B75: Formwork to soffits of suspended slabs <= 3.5 m props incl props | C75: m2 | D75: G-SHT | E75: 1.3 | F75: =IF(D75="",0,E75*INDEX(Gangs!$D:$D,MATCH(D75,Gangs!$A:$A,0))) -> 215.96224 | G75: FWMAT | H75: 1 | M75: =IF(G75="",0,H75*INDEX(Materials!$E:$E,MATCH(G75,Materials!$A:$A,0)))+IF(I75="",0,J75*INDEX(Materials!$E:$E,MATCH(I75,Materials!$A:$A,0)))+IF(K75="",0,L75*INDEX(Materials!$E:$E,MATCH(K75,Materials!$A:$A,0))) -> 88 | N75: 0 | O75: P-PROPS | P75: 1 | Q75: =IF(O75="",0,P75*INDEX(Plant!$D:$D,MATCH(O75,Plant!$A:$A,0))) -> 45 | R75: =F75+M75+N75+Q75 -> 348.96224 | S75: =R75*Settings!$B$4*Settings!$B$9 -> 348.96224 | T75: =S75*(1+Settings!$B$10) -> 408.28582
A76: CN18 | B76: Formwork to columns | C76: m2 | D76: G-SHT | E76: 1.8 | F76: =IF(D76="",0,E76*INDEX(Gangs!$D:$D,MATCH(D76,Gangs!$A:$A,0))) -> 299.02464 | G76: FWMAT | H76: 1.1 | M76: =IF(G76="",0,H76*INDEX(Materials!$E:$E,MATCH(G76,Materials!$A:$A,0)))+IF(I76="",0,J76*INDEX(Materials!$E:$E,MATCH(I76,Materials!$A:$A,0)))+IF(K76="",0,L76*INDEX(Materials!$E:$E,MATCH(K76,Materials!$A:$A,0))) -> 96.8 | N76: 0 | Q76: =IF(O76="",0,P76*INDEX(Plant!$D:$D,MATCH(O76,Plant!$A:$A,0))) -> 0 | R76: =F76+M76+N76+Q76 -> 395.82464 | S76: =R76*Settings!$B$4*Settings!$B$9 -> 395.82464 | T76: =S76*(1+Settings!$B$10) -> 463.11483
A77: CN19 | B77: Formwork to edges of slabs <= 300 mm | C77: m | D77: G-SHT | E77: 0.35 | F77: =IF(D77="",0,E77*INDEX(Gangs!$D:$D,MATCH(D77,Gangs!$A:$A,0))) -> 58.14368 | G77: FWMAT | H77: 0.3 | M77: =IF(G77="",0,H77*INDEX(Materials!$E:$E,MATCH(G77,Materials!$A:$A,0)))+IF(I77="",0,J77*INDEX(Materials!$E:$E,MATCH(I77,Materials!$A:$A,0)))+IF(K77="",0,L77*INDEX(Materials!$E:$E,MATCH(K77,Materials!$A:$A,0))) -> 26.4 | N77: 0 | Q77: =IF(O77="",0,P77*INDEX(Plant!$D:$D,MATCH(O77,Plant!$A:$A,0))) -> 0 | R77: =F77+M77+N77+Q77 -> 84.54368 | S77: =R77*Settings!$B$4*Settings!$B$9 -> 84.54368 | T77: =S77*(1+Settings!$B$10) -> 98.916106
A78: CN20 | B78: High-yield reinforcement Y10-Y16, cut, bent & fixed | C78: t | D78: G-STF | E78: 32 | F78: =IF(D78="",0,E78*INDEX(Gangs!$D:$D,MATCH(D78,Gangs!$A:$A,0))) -> 5315.9936 | G78: REBAR | H78: 1.03 | I78: TIEW | J78: 8 | M78: =IF(G78="",0,H78*INDEX(Materials!$E:$E,MATCH(G78,Materials!$A:$A,0)))+IF(I78="",0,J78*INDEX(Materials!$E:$E,MATCH(I78,Materials!$A:$A,0)))+IF(K78="",0,L78*INDEX(Materials!$E:$E,MATCH(K78,Materials!$A:$A,0))) -> 20730 | N78: 0 | Q78: =IF(O78="",0,P78*INDEX(Plant!$D:$D,MATCH(O78,Plant!$A:$A,0))) -> 0 | R78: =F78+M78+N78+Q78 -> 26045.994 | S78: =R78*Settings!$B$4*Settings!$B$9 -> 26045.994 | T78: =S78*(1+Settings!$B$10) -> 30473.813
A79: CN21 | B79: High-yield reinforcement Y20-Y32, cut, bent & fixed | C79: t | D79: G-STF | E79: 24 | F79: =IF(D79="",0,E79*INDEX(Gangs!$D:$D,MATCH(D79,Gangs!$A:$A,0))) -> 3986.9952 | G79: REBAR | H79: 1.03 | I79: TIEW | J79: 6 | M79: =IF(G79="",0,H79*INDEX(Materials!$E:$E,MATCH(G79,Materials!$A:$A,0)))+IF(I79="",0,J79*INDEX(Materials!$E:$E,MATCH(I79,Materials!$A:$A,0)))+IF(K79="",0,L79*INDEX(Materials!$E:$E,MATCH(K79,Materials!$A:$A,0))) -> 20646 | N79: 0 | Q79: =IF(O79="",0,P79*INDEX(Plant!$D:$D,MATCH(O79,Plant!$A:$A,0))) -> 0 | R79: =F79+M79+N79+Q79 -> 24632.995 | S79: =R79*Settings!$B$4*Settings!$B$9 -> 24632.995 | T79: =S79*(1+Settings!$B$10) -> 28820.604
A80: CN22 | B80: Mild steel reinforcement <= R10, cut, bent & fixed | C80: t | D80: G-STF | E80: 40 | F80: =IF(D80="",0,E80*INDEX(Gangs!$D:$D,MATCH(D80,Gangs!$A:$A,0))) -> 6644.992 | G80: REBARMS | H80: 1.03 | I80: TIEW | J80: 10 | M80: =IF(G80="",0,H80*INDEX(Materials!$E:$E,MATCH(G80,Materials!$A:$A,0)))+IF(I80="",0,J80*INDEX(Materials!$E:$E,MATCH(I80,Materials!$A:$A,0)))+IF(K80="",0,L80*INDEX(Materials!$E:$E,MATCH(K80,Materials!$A:$A,0))) -> 20196 | N80: 0 | Q80: =IF(O80="",0,P80*INDEX(Plant!$D:$D,MATCH(O80,Plant!$A:$A,0))) -> 0 | R80: =F80+M80+N80+Q80 -> 26840.992 | S80: =R80*Settings!$B$4*Settings!$B$9 -> 26840.992 | T80: =S80*(1+Settings!$B$10) -> 31403.961
A81: CN23 | B81: Fabric reinforcement Ref 193 incl laps & spacers | C81: m2 | D81: G-STF | E81: 0.05 | F81: =IF(D81="",0,E81*INDEX(Gangs!$D:$D,MATCH(D81,Gangs!$A:$A,0))) -> 8.30624 | G81: MESH193 | H81: 1.15 | M81: =IF(G81="",0,H81*INDEX(Materials!$E:$E,MATCH(G81,Materials!$A:$A,0)))+IF(I81="",0,J81*INDEX(Materials!$E:$E,MATCH(I81,Materials!$A:$A,0)))+IF(K81="",0,L81*INDEX(Materials!$E:$E,MATCH(K81,Materials!$A:$A,0))) -> 59.8 | N81: 2 | Q81: =IF(O81="",0,P81*INDEX(Plant!$D:$D,MATCH(O81,Plant!$A:$A,0))) -> 0 | R81: =F81+M81+N81+Q81 -> 70.10624 | S81: =R81*Settings!$B$4*Settings!$B$9 -> 70.10624 | T81: =S81*(1+Settings!$B$10) -> 82.024301
A82: CN24 | B82: Fabric reinforcement Ref 245 incl laps & spacers | C82: m2 | D82: G-STF | E82: 0.06 | F82: =IF(D82="",0,E82*INDEX(Gangs!$D:$D,MATCH(D82,Gangs!$A:$A,0))) -> 9.967488 | G82: MESH245 | H82: 1.15 | M82: =IF(G82="",0,H82*INDEX(Materials!$E:$E,MATCH(G82,Materials!$A:$A,0)))+IF(I82="",0,J82*INDEX(Materials!$E:$E,MATCH(I82,Materials!$A:$A,0)))+IF(K82="",0,L82*INDEX(Materials!$E:$E,MATCH(K82,Materials!$A:$A,0))) -> 75.9 | N82: 2 | Q82: =IF(O82="",0,P82*INDEX(Plant!$D:$D,MATCH(O82,Plant!$A:$A,0))) -> 0 | R82: =F82+M82+N82+Q82 -> 87.867488 | S82: =R82*Settings!$B$4*Settings!$B$9 -> 87.867488 | T82: =S82*(1+Settings!$B$10) -> 102.80496
A83: CN25 | B83: Fabric reinforcement Ref 100 incl laps & spacers | C83: m2 | D83: G-STF | E83: 0.04 | F83: =IF(D83="",0,E83*INDEX(Gangs!$D:$D,MATCH(D83,Gangs!$A:$A,0))) -> 6.644992 | G83: MESH100 | H83: 1.15 | M83: =IF(G83="",0,H83*INDEX(Materials!$E:$E,MATCH(G83,Materials!$A:$A,0)))+IF(I83="",0,J83*INDEX(Materials!$E:$E,MATCH(I83,Materials!$A:$A,0)))+IF(K83="",0,L83*INDEX(Materials!$E:$E,MATCH(K83,Materials!$A:$A,0))) -> 35.65 | N83: 2 | Q83: =IF(O83="",0,P83*INDEX(Plant!$D:$D,MATCH(O83,Plant!$A:$A,0))) -> 0 | R83: =F83+M83+N83+Q83 -> 44.294992 | S83: =R83*Settings!$B$4*Settings!$B$9 -> 44.294992 | T83: =S83*(1+Settings!$B$10) -> 51.825141
A84: CN26 | B84: Construction / isolation joint incl filler & sealant | C84: m | D84: G-SCR | E84: 0.15 | F84: =IF(D84="",0,E84*INDEX(Gangs!$D:$D,MATCH(D84,Gangs!$A:$A,0))) -> 24.91872 | G84: JSEAL | H84: 1.05 | M84: =IF(G84="",0,H84*INDEX(Materials!$E:$E,MATCH(G84,Materials!$A:$A,0)))+IF(I84="",0,J84*INDEX(Materials!$E:$E,MATCH(I84,Materials!$A:$A,0)))+IF(K84="",0,L84*INDEX(Materials!$E:$E,MATCH(K84,Materials!$A:$A,0))) -> 29.4 | N84: 0 | Q84: =IF(O84="",0,P84*INDEX(Plant!$D:$D,MATCH(O84,Plant!$A:$A,0))) -> 0 | R84: =F84+M84+N84+Q84 -> 54.31872 | S84: =R84*Settings!$B$4*Settings!$B$9 -> 54.31872 | T84: =S84*(1+Settings!$B$10) -> 63.552902
A85: CN27 | B85: Saw-cut contraction joint & seal | C85: m | D85: G-SCR | E85: 0.1 | F85: =IF(D85="",0,E85*INDEX(Gangs!$D:$D,MATCH(D85,Gangs!$A:$A,0))) -> 16.61248 | G85: JSEAL | H85: 1 | M85: =IF(G85="",0,H85*INDEX(Materials!$E:$E,MATCH(G85,Materials!$A:$A,0)))+IF(I85="",0,J85*INDEX(Materials!$E:$E,MATCH(I85,Materials!$A:$A,0)))+IF(K85="",0,L85*INDEX(Materials!$E:$E,MATCH(K85,Materials!$A:$A,0))) -> 28 | N85: 0 | O85: P-SAW | P85: 0.02 | Q85: =IF(O85="",0,P85*INDEX(Plant!$D:$D,MATCH(O85,Plant!$A:$A,0))) -> 14 | R85: =F85+M85+N85+Q85 -> 58.61248 | S85: =R85*Settings!$B$4*Settings!$B$9 -> 58.61248 | T85: =S85*(1+Settings!$B$10) -> 68.576602
A86: CN28 | B86: Precast prestressed lintel 110 mm, bedded | C86: m | D86: G-BRK | E86: 0.12 | F86: =IF(D86="",0,E86*INDEX(Gangs!$D:$D,MATCH(D86,Gangs!$A:$A,0))) -> 19.934976 | G86: LINT | H86: 1 | I86: MORT | J86: 0.001 | M86: =IF(G86="",0,H86*INDEX(Materials!$E:$E,MATCH(G86,Materials!$A:$A,0)))+IF(I86="",0,J86*INDEX(Materials!$E:$E,MATCH(I86,Materials!$A:$A,0)))+IF(K86="",0,L86*INDEX(Materials!$E:$E,MATCH(K86,Materials!$A:$A,0))) -> 79.148 | N86: 0 | Q86: =IF(O86="",0,P86*INDEX(Plant!$D:$D,MATCH(O86,Plant!$A:$A,0))) -> 0 | R86: =F86+M86+N86+Q86 -> 99.082976 | S86: =R86*Settings!$B$4*Settings!$B$9 -> 99.082976 | T86: =S86*(1+Settings!$B$10) -> 115.92708
A87: CN29 | B87: Rib-and-block suspended slab 250 mm incl 50 mm 30 MPa topping & mesh (props hire incl) | C87: m2 | D87: G-CON | E87: 0.5 | F87: =IF(D87="",0,E87*INDEX(Gangs!$D:$D,MATCH(D87,Gangs!$A:$A,0))) -> 144.13845 | G87: RIBBLK | H87: 1 | I87: RM30 | J87: 0.075 | K87: MESH100 | L87: 1.15 | M87: =IF(G87="",0,H87*INDEX(Materials!$E:$E,MATCH(G87,Materials!$A:$A,0)))+IF(I87="",0,J87*INDEX(Materials!$E:$E,MATCH(I87,Materials!$A:$A,0)))+IF(K87="",0,L87*INDEX(Materials!$E:$E,MATCH(K87,Materials!$A:$A,0))) -> 550.65 | N87: 0 | O87: P-PROPS | P87: 1 | Q87: =IF(O87="",0,P87*INDEX(Plant!$D:$D,MATCH(O87,Plant!$A:$A,0))) -> 45 | R87: =F87+M87+N87+Q87 -> 739.78845 | S87: =R87*Settings!$B$4*Settings!$B$9 -> 739.78845 | T87: =S87*(1+Settings!$B$10) -> 865.55249
A88: MASONRY
A89: MS01 | B89: Half-brick wall, clay stock NFP, Class II mortar, brickforce every 4th course | C89: m2 | D89: G-BRK | E89: 0.85 | F89: =IF(D89="",0,E89*INDEX(Gangs!$D:$D,MATCH(D89,Gangs!$A:$A,0))) -> 141.20608 | G89: BRKCLAY | H89: 55 | I89: MORT | J89: 0.02 | K89: BFORCE | L89: 1.6 | M89: =IF(G89="",0,H89*INDEX(Materials!$E:$E,MATCH(G89,Materials!$A:$A,0)))+IF(I89="",0,J89*INDEX(Materials!$E:$E,MATCH(I89,Materials!$A:$A,0)))+IF(K89="",0,L89*INDEX(Materials!$E:$E,MATCH(K89,Materials!$A:$A,0))) -> 148.92 | N89: 0 | Q89: =IF(O89="",0,P89*INDEX(Plant!$D:$D,MATCH(O89,Plant!$A:$A,0))) -> 0 | R89: =F89+M89+N89+Q89 -> 290.12608 | S89: =R89*Settings!$B$4*Settings!$B$9 -> 290.12608 | T89: =S89*(1+Settings!$B$10) -> 339.44751
A90: MS02 | B90: One-brick wall, clay stock NFP | C90: m2 | D90: G-BRK | E90: 1.6 | F90: =IF(D90="",0,E90*INDEX(Gangs!$D:$D,MATCH(D90,Gangs!$A:$A,0))) -> 265.79968 | G90: BRKCLAY | H90: 110 | I90: MORT | J90: 0.05 | K90: BFORCE | L90: 3.2 | M90: =IF(G90="",0,H90*INDEX(Materials!$E:$E,MATCH(G90,Materials!$A:$A,0)))+IF(I90="",0,J90*INDEX(Materials!$E:$E,MATCH(I90,Materials!$A:$A,0)))+IF(K90="",0,L90*INDEX(Materials!$E:$E,MATCH(K90,Materials!$A:$A,0))) -> 309.32 | N90: 0 | Q90: =IF(O90="",0,P90*INDEX(Plant!$D:$D,MATCH(O90,Plant!$A:$A,0))) -> 0 | R90: =F90+M90+N90+Q90 -> 575.11968 | S90: =R90*Settings!$B$4*Settings!$B$9 -> 575.11968 | T90: =S90*(1+Settings!$B$10) -> 672.89003
A91: MS03 | B91: Half-brick wall, cement stock brick | C91: m2 | D91: G-BRK | E91: 0.85 | F91: =IF(D91="",0,E91*INDEX(Gangs!$D:$D,MATCH(D91,Gangs!$A:$A,0))) -> 141.20608 | G91: BRKCEM | H91: 55 | I91: MORT | J91: 0.02 | K91: BFORCE | L91: 1.6 | M91: =IF(G91="",0,H91*INDEX(Materials!$E:$E,MATCH(G91,Materials!$A:$A,0)))+IF(I91="",0,J91*INDEX(Materials!$E:$E,MATCH(I91,Materials!$A:$A,0)))+IF(K91="",0,L91*INDEX(Materials!$E:$E,MATCH(K91,Materials!$A:$A,0))) -> 143.42 | N91: 0 | Q91: =IF(O91="",0,P91*INDEX(Plant!$D:$D,MATCH(O91,Plant!$A:$A,0))) -> 0 | R91: =F91+M91+N91+Q91 -> 284.62608 | S91: =R91*Settings!$B$4*Settings!$B$9 -> 284.62608 | T91: =S91*(1+Settings!$B$10) -> 333.01251
A92: MS04 | B92: One-brick wall, cement stock brick | C92: m2 | D92: G-BRK | E92: 1.6 | F92: =IF(D92="",0,E92*INDEX(Gangs!$D:$D,MATCH(D92,Gangs!$A:$A,0))) -> 265.79968 | G92: BRKCEM | H92: 110 | I92: MORT | J92: 0.05 | K92: BFORCE | L92: 3.2 | M92: =IF(G92="",0,H92*INDEX(Materials!$E:$E,MATCH(G92,Materials!$A:$A,0)))+IF(I92="",0,J92*INDEX(Materials!$E:$E,MATCH(I92,Materials!$A:$A,0)))+IF(K92="",0,L92*INDEX(Materials!$E:$E,MATCH(K92,Materials!$A:$A,0))) -> 298.32 | N92: 0 | Q92: =IF(O92="",0,P92*INDEX(Plant!$D:$D,MATCH(O92,Plant!$A:$A,0))) -> 0 | R92: =F92+M92+N92+Q92 -> 564.11968 | S92: =R92*Settings!$B$4*Settings!$B$9 -> 564.11968 | T92: =S92*(1+Settings!$B$10) -> 660.02003
A93: MS05 | B93: 280 mm cavity wall, 2 x half-brick clay stock incl ties (4/m2) | C93: m2 | D93: G-BRK | E93: 1.8 | F93: =IF(D93="",0,E93*INDEX(Gangs!$D:$D,MATCH(D93,Gangs!$A:$A,0))) -> 299.02464 | G93: BRKCLAY | H93: 110 | I93: MORT | J93: 0.042 | K93: TIES | L93: 4 | M93: =IF(G93="",0,H93*INDEX(Materials!$E:$E,MATCH(G93,Materials!$A:$A,0)))+IF(I93="",0,J93*INDEX(Materials!$E:$E,MATCH(I93,Materials!$A:$A,0)))+IF(K93="",0,L93*INDEX(Materials!$E:$E,MATCH(K93,Materials!$A:$A,0))) -> 296.616 | N93: 10 | Q93: =IF(O93="",0,P93*INDEX(Plant!$D:$D,MATCH(O93,Plant!$A:$A,0))) -> 0 | R93: =F93+M93+N93+Q93 -> 605.64064 | S93: =R93*Settings!$B$4*Settings!$B$9 -> 605.64064 | T93: =S93*(1+Settings!$B$10) -> 708.59955
A94: MS06 | B94: 140 mm cement block wall | C94: m2 | D94: G-BRK | E94: 0.6 | F94: =IF(D94="",0,E94*INDEX(Gangs!$D:$D,MATCH(D94,Gangs!$A:$A,0))) -> 99.67488 | G94: BLK140 | H94: 13 | I94: MORT | J94: 0.011 | K94: BFORCE | L94: 1.3 | M94: =IF(G94="",0,H94*INDEX(Materials!$E:$E,MATCH(G94,Materials!$A:$A,0)))+IF(I94="",0,J94*INDEX(Materials!$E:$E,MATCH(I94,Materials!$A:$A,0)))+IF(K94="",0,L94*INDEX(Materials!$E:$E,MATCH(K94,Materials!$A:$A,0))) -> 192.158 | N94: 0 | Q94: =IF(O94="",0,P94*INDEX(Plant!$D:$D,MATCH(O94,Plant!$A:$A,0))) -> 0 | R94: =F94+M94+N94+Q94 -> 291.83288 | S94: =R94*Settings!$B$4*Settings!$B$9 -> 291.83288 | T94: =S94*(1+Settings!$B$10) -> 341.44447
A95: MS07 | B95: 190 mm cement block wall | C95: m2 | D95: G-BRK | E95: 0.7 | F95: =IF(D95="",0,E95*INDEX(Gangs!$D:$D,MATCH(D95,Gangs!$A:$A,0))) -> 116.28736 | G95: BLK190 | H95: 13 | I95: MORT | J95: 0.014 | K95: BFORCE | L95: 1.3 | M95: =IF(G95="",0,H95*INDEX(Materials!$E:$E,MATCH(G95,Materials!$A:$A,0)))+IF(I95="",0,J95*INDEX(Materials!$E:$E,MATCH(I95,Materials!$A:$A,0)))+IF(K95="",0,L95*INDEX(Materials!$E:$E,MATCH(K95,Materials!$A:$A,0))) -> 252.802 | N95: 0 | Q95: =IF(O95="",0,P95*INDEX(Plant!$D:$D,MATCH(O95,Plant!$A:$A,0))) -> 0 | R95: =F95+M95+N95+Q95 -> 369.08936 | S95: =R95*Settings!$B$4*Settings!$B$9 -> 369.08936 | T95: =S95*(1+Settings!$B$10) -> 431.83455
A96: MS08 | B96: 90 mm cement block partition | C96: m2 | D96: G-BRK | E96: 0.5 | F96: =IF(D96="",0,E96*INDEX(Gangs!$D:$D,MATCH(D96,Gangs!$A:$A,0))) -> 83.0624 | G96: BLK90 | H96: 13 | I96: MORT | J96: 0.008 | M96: =IF(G96="",0,H96*INDEX(Materials!$E:$E,MATCH(G96,Materials!$A:$A,0)))+IF(I96="",0,J96*INDEX(Materials!$E:$E,MATCH(I96,Materials!$A:$A,0)))+IF(K96="",0,L96*INDEX(Materials!$E:$E,MATCH(K96,Materials!$A:$A,0))) -> 136.584 | N96: 0 | Q96: =IF(O96="",0,P96*INDEX(Plant!$D:$D,MATCH(O96,Plant!$A:$A,0))) -> 0 | R96: =F96+M96+N96+Q96 -> 219.6464 | S96: =R96*Settings!$B$4*Settings!$B$9 -> 219.6464 | T96: =S96*(1+Settings!$B$10) -> 256.98629
A97: MS09 | B97: Half-brick face brick wall, pointed one side | C97: m2 | D97: G-BRKF | E97: 1.2 | F97: =IF(D97="",0,E97*INDEX(Gangs!$D:$D,MATCH(D97,Gangs!$A:$A,0))) -> 244.49952 | G97: FACEBRK | H97: 55 | I97: MORT | J97: 0.02 | K97: BFORCE | L97: 1.6 | M97: =IF(G97="",0,H97*INDEX(Materials!$E:$E,MATCH(G97,Materials!$A:$A,0)))+IF(I97="",0,J97*INDEX(Materials!$E:$E,MATCH(I97,Materials!$A:$A,0)))+IF(K97="",0,L97*INDEX(Materials!$E:$E,MATCH(K97,Materials!$A:$A,0))) -> 324.92 | N97: 0 | Q97: =IF(O97="",0,P97*INDEX(Plant!$D:$D,MATCH(O97,Plant!$A:$A,0))) -> 0 | R97: =F97+M97+N97+Q97 -> 569.41952 | S97: =R97*Settings!$B$4*Settings!$B$9 -> 569.41952 | T97: =S97*(1+Settings!$B$10) -> 666.22084
A98: MS10 | B98: One-brick wall, face one side / stock other | C98: m2 | D98: G-BRKF | E98: 1.9 | F98: =IF(D98="",0,E98*INDEX(Gangs!$D:$D,MATCH(D98,Gangs!$A:$A,0))) -> 387.12424 | G98: FACEBRK | H98: 55 | I98: BRKCLAY | J98: 55 | K98: MORT | L98: 0.05 | M98: =IF(G98="",0,H98*INDEX(Materials!$E:$E,MATCH(G98,Materials!$A:$A,0)))+IF(I98="",0,J98*INDEX(Materials!$E:$E,MATCH(I98,Materials!$A:$A,0)))+IF(K98="",0,L98*INDEX(Materials!$E:$E,MATCH(K98,Materials!$A:$A,0))) -> 475.4 | N98: 5 | Q98: =IF(O98="",0,P98*INDEX(Plant!$D:$D,MATCH(O98,Plant!$A:$A,0))) -> 0 | R98: =F98+M98+N98+Q98 -> 867.52424 | S98: =R98*Settings!$B$4*Settings!$B$9 -> 867.52424 | T98: =S98*(1+Settings!$B$10) -> 1015.0034
A99: MS11 | B99: 280 mm cavity wall, face brick outer / stock inner incl ties | C99: m2 | D99: G-BRKF | E99: 2 | F99: =IF(D99="",0,E99*INDEX(Gangs!$D:$D,MATCH(D99,Gangs!$A:$A,0))) -> 407.4992 | G99: FACEBRK | H99: 55 | I99: BRKCLAY | J99: 55 | K99: MORT | L99: 0.042 | M99: =IF(G99="",0,H99*INDEX(Materials!$E:$E,MATCH(G99,Materials!$A:$A,0)))+IF(I99="",0,J99*INDEX(Materials!$E:$E,MATCH(I99,Materials!$A:$A,0)))+IF(K99="",0,L99*INDEX(Materials!$E:$E,MATCH(K99,Materials!$A:$A,0))) -> 466.216 | N99: 12 | Q99: =IF(O99="",0,P99*INDEX(Plant!$D:$D,MATCH(O99,Plant!$A:$A,0))) -> 0 | R99: =F99+M99+N99+Q99 -> 885.7152 | S99: =R99*Settings!$B$4*Settings!$B$9 -> 885.7152 | T99: =S99*(1+Settings!$B$10) -> 1036.2868
A100: MS12 | B100: One-brick wall in foundations, cement stock, Class I mortar | C100: m2 | D100: G-BRK | E100: 1.4 | F100: =IF(D100="",0,E100*INDEX(Gangs!$D:$D,MATCH(D100,Gangs!$A:$A,0))) -> 232.57472 | G100: BRKCEM | H100: 110 | I100: MORT | J100: 0.05 | M100: =IF(G100="",0,H100*INDEX(Materials!$E:$E,MATCH(G100,Materials!$A:$A,0)))+IF(I100="",0,J100*INDEX(Materials!$E:$E,MATCH(I100,Materials!$A:$A,0)))+IF(K100="",0,L100*INDEX(Materials!$E:$E,MATCH(K100,Materials!$A:$A,0))) -> 288.4 | N100: 0 | Q100: =IF(O100="",0,P100*INDEX(Plant!$D:$D,MATCH(O100,Plant!$A:$A,0))) -> 0 | R100: =F100+M100+N100+Q100 -> 520.97472 | S100: =R100*Settings!$B$4*Settings!$B$9 -> 520.97472 | T100: =S100*(1+Settings!$B$10) -> 609.54042
A101: MS13 | B101: Brickforce, extra | C101: m | D101: G-BRK | E101: 0.01 | F101: =IF(D101="",0,E101*INDEX(Gangs!$D:$D,MATCH(D101,Gangs!$A:$A,0))) -> 1.661248 | G101: BFORCE | H101: 1.05 | M101: =IF(G101="",0,H101*INDEX(Materials!$E:$E,MATCH(G101,Materials!$A:$A,0)))+IF(I101="",0,J101*INDEX(Materials!$E:$E,MATCH(I101,Materials!$A:$A,0)))+IF(K101="",0,L101*INDEX(Materials!$E:$E,MATCH(K101,Materials!$A:$A,0))) -> 3.255 | N101: 0 | Q101: =IF(O101="",0,P101*INDEX(Plant!$D:$D,MATCH(O101,Plant!$A:$A,0))) -> 0 | R101: =F101+M101+N101+Q101 -> 4.916248 | S101: =R101*Settings!$B$4*Settings!$B$9 -> 4.916248 | T101: =S101*(1+Settings!$B$10) -> 5.7520102
...

Sheet Materials
A1: Code | B1: Category | C1: Description | D1: Unit | E1: Price ex VAT (R) | F1: Basis | G1: Source / note
A2: CEM | B2: Aggregates & binders | C2: Cement CEM II 42.5N, 50 kg bag | D2: bag | E2: 98 | F2: MARKET | G2: Gauteng R95-R120 incl VAT (handyman JHB 2026 guide)
A3: LIME | B3: Aggregates & binders | C3: Builders lime, 25 kg bag | D3: bag | E3: 72 | F3: QS ESTIMATE
A4: BSAND | B4: Aggregates & binders | C4: Building sand, delivered | D4: m3 | E4: 420 | F4: MARKET | G4: R350-R550/m3 (JHB 2026 guide)
A5: PSAND | B5: Aggregates & binders | C5: Plaster sand, delivered | D5: m3 | E5: 390 | F5: MARKET | G5: R300-R450/m3
A6: RSAND | B6: Aggregates & binders | C6: River / concrete sand, delivered | D6: m3 | E6: 480 | F6: MARKET | G6: Premium over building sand
A7: STONE19 | B7: Aggregates & binders | C7: 19 mm crushed stone, delivered | D7: m3 | E7: 560 | F7: MARKET | G7: R400-R700/m3
A8: G5 | B8: Aggregates & binders | C8: Imported G5 selected fill, delivered | D8: m3 | E8: 300 | F8: QS ESTIMATE
A9: MORT | B9: Composites | C9: Class II mortar 1:4 (7 bags cement + 1.1 m3 building sand) | D9: m3 | E9: =7*E2+1.1*E4 -> 1148 | F9: COMPOSITE | G9: Formula
A10: PLASMIX | B10: Composites | C10: Plaster 1:5 (6 bags cement + 1.15 m3 plaster sand) | D10: m3 | E10: =6*E2+1.15*E5 -> 1036.5 | F10: COMPOSITE | G10: Formula
A11: CSITE | B11: Composites | C11: Site-mixed 25 MPa concrete (7 bags + 0.65 sand + 0.75 stone) — PPC ~6.7 bags/m3 for 20-29 MPa | D11: m3 | E11: =7*E2+0.65*E6+0.75*E7 -> 1418 | F11: COMPOSITE | G11: Formula; PPC mix guidance
A12: SCREEDMIX | B12: Composites | C12: Screed 1:4 (8 bags cement + 1.1 m3 river sand) | D12: m3 | E12: =8*E2+1.1*E6 -> 1312 | F12: COMPOSITE | G12: Formula
A13: RM15 | B13: Concrete | C13: Readymix 15 MPa / 19 mm, delivered (full loads) | D13: m3 | E13: 1520 | F13: QS ESTIMATE | G13: Readymix R1,200-R1,800/m3 market range
A14: RM20 | B14: Concrete | C14: Readymix 20 MPa | D14: m3 | E14: 1600 | F14: QS ESTIMATE
A15: RM25 | B15: Concrete | C15: Readymix 25 MPa | D15: m3 | E15: 1690 | F15: QS ESTIMATE
A16: RM30 | B16: Concrete | C16: Readymix 30 MPa | D16: m3 | E16: 1800 | F16: QS ESTIMATE
A17: RM35 | B17: Concrete | C17: Readymix 35 MPa | D17: m3 | E17: 1930 | F17: QS ESTIMATE
A18: REBAR | B18: Reinforcement | C18: High-yield Y-bar, scheduled, cut & bent, delivered | D18: t | E18: 19800 | F18: QS ESTIMATE
A19: REBARMS | B19: Reinforcement | C19: Mild steel R-bar, cut & bent, delivered | D19: t | E19: 19200 | F19: QS ESTIMATE
A20: MESH193 | B20: Reinforcement | C20: Fabric mesh Ref 193 | D20: m2 | E20: 52 | F20: QS ESTIMATE
A21: MESH245 | B21: Reinforcement | C21: Fabric mesh Ref 245 | D21: m2 | E21: 66 | F21: QS ESTIMATE
A22: MESH100 | B22: Reinforcement | C22: Fabric mesh Ref 100 | D22: m2 | E22: 31 | F22: QS ESTIMATE
A23: TIEW | B23: Reinforcement | C23: Binding wire | D23: kg | E23: 42 | F23: QS ESTIMATE
A24: FWMAT | B24: Formwork | C24: Formwork materials (18 mm shutter ply + timber, 4 uses) | D24: m2 | E24: 88 | F24: QS ESTIMATE
A25: DPM250 | B25: Concrete | C25: 250 micron DPM (SANS 952) | D25: m2 | E25: 7.5 | F25: QS ESTIMATE
... A28: RIBBLK | B28: Concrete | C28: Rib-and-block suspended slab system (beams + blocks, excl topping) | D28: m2 | E28: 380 | F28: QS ESTIMATE
A29: BRKCLAY | B29: Masonry | C29: Clay stock brick NFP 222x106x73 | D29: no | E29: 2.2 | F29: MARKET | G29: R1,600-R2,500 per 1,000
A30: BRKCEM | B30: Masonry | C30: Cement stock brick NFX | D30: no | E30: 2.1 | F30: MARKET | G30: R1,800-R3,000 per 1,000
A31: FACEBRK | B31: Masonry | C31: Clay face brick (PC) | D31: no | E31: 5.4 | F31: MARKET | G31: R3,500-R6,000 per 1,000
A32: BLK90 | B32: Masonry | C32: Cement block 390x190x90 | D32: no | E32: 9.8 | F32: QS ESTIMATE
A33: BLK140 | B33: Masonry | C33: Cement block 390x190x140 | D33: no | E33: 13.5 | F33: QS ESTIMATE
A34: BLK190 | B34: Masonry | C34: Cement block 390x190x190 | D34: no | E34: 17.9 | F34: QS ESTIMATE
A35: BFORCE | B35: Masonry | C35: Brickforce 150 mm | D35: m | E35: 3.1 | F35: QS ESTIMATE
A36: TIES | B36: Masonry | C36: Galvanised wire wall tie | D36: no | E36: 1.6 | F36: QS ESTIMATE
A37: DPC375 | B37: Masonry | C37: Embossed polyolefin DPC 375 mm | D37: m | E37: 7.5 | F37: QS ESTIMATE
A38: DPC230 | B38: Masonry | C38: Embossed polyolefin DPC 230 mm | D38: m | E38: 4.6 | F38: QS ESTIMATE
A39: HOOP | B39: Masonry | C39: Galvanised hoop iron 30x1.6 | D39: m | E39: 4.5 | F39: QS ESTIMATE
A40: TRUSS | B40: Roofing | C40: Engineered timber trusses incl hangers & bracing, delivered (per m2 plan) | D40: m2 | E40: 330 | F40: QS ESTIMATE | G40: Truss cost R250-R650/m2 excl covering (Complete Roofing 2026)
A41: TIM114 | B41: Roofing | C41: SA pine S5 38x114 | D41: m | E41: 44 | F41: QS ESTIMATE
A42: TIM152 | B42: Roofing | C42: SA pine S5 38x152 | D42: m | E42: 60 | F42: QS ESTIMATE
A43: BAT38 | B43: Roofing | C43: SA pine batten / brandering 38x38 | D43: m | E43: 10.5 | F43: QS ESTIMATE
A44: CTILE | B44: Roofing | C44: Concrete roof tiles incl 5% cuts allowance | D44: m2 | E44: 165 | F44: QS ESTIMATE
A45: CLAYTILE | B45: Roofing | C45: Clay roof tiles | D45: m2 | E45: 330 | F45: QS ESTIMATE
A46: UNDERL | B46: Roofing | C46: Roof underlay (breathable) | D46: m2 | E46: 17 | F46: QS ESTIMATE
A47: IBR05 | B47: Roofing | C47: IBR 0.50 mm pre-painted (Chromadek), per m2 cover | D47: m2 | E47: 185 | F47: QS ESTIMATE
A48: IBR047 | B48: Roofing | C48: IBR 0.47 mm Zincalume, per m2 cover | D48: m2 | E48: 150 | F48: QS ESTIMATE
A49: CORR05 | B49: Roofing | C49: Corrugated 0.50 mm galvanised, per m2 cover | D49: m2 | E49: 145 | F49: QS ESTIMATE
A50: PURLIN | B50: Roofing | C50: Lipped channel purlin 100x50x20x2.0 | D50: m | E50: 95 | F50: QS ESTIMATE
A51: RIDGE | B51: Roofing | C51: Concrete ridge / hip tile | D51: no | E51: 26 | F51: QS ESTIMATE
A52: RIDGEIBR | B52: Roofing | C52: Pre-painted ridge capping | D52: m | E52: 110 | F52: QS ESTIMATE
... A54: FASCIA | B54: Roofing | C54: Fibre-cement fascia / barge 225 mm | D54: m | E54: 92 | F54: QS ESTIMATE
A55: GUTTER | B55: Roofing | C55: Seamless aluminium gutter 125 mm — installed | D55: m | E55: 260 | F55: QS ESTIMATE | G55: Supply & fix subcontract
A56: DPIPE | B56: Roofing | C56: Aluminium downpipe 75 mm | D56: m | E56: 85 | F56: QS ESTIMATE
A57: ISO135 | B57: Roofing | C57: Polyester ceiling insulation 135 mm (SANS 10400-XA) | D57: m2 | E57: 92 | F57: QS ESTIMATE
A58: GLASS100 | B58: Roofing | C58: Glasswool insulation 100 mm | D58: m2 | E58: 68 | F58: QS ESTIMATE
A59: FOIL | B59: Roofing | C59: Reflective foil / sisalation | D59: m2 | E59: 22 | F59: QS ESTIMATE
A60: THATCH | B60: Roofing | C60: Thatch 200 mm incl poles & SANS fire treatment — installed | D60: m2 | E60: 950 | F60: MARKET | G60: R500-R800 base, premium to R2,000 (2026)
A61: POLYC | B61: Roofing | C61: Polycarbonate sheeting 10 mm multiwall | D61: m2 | E61: 480 | F61: QS ESTIMATE
A62: DOORHC | B62: Joinery | C62: Hollow-core flush door 813x2032 | D62: no | E62: 620 | F62: QS ESTIMATE
A63: DOORSS | B63: Joinery | C63: Semi-solid door 813x2032 | D63: no | E63: 1450 | F63: QS ESTIMATE
A64: DOOREXT | B64: Joinery | C64: Solid meranti external door | D64: no | E64: 3600 | F64: QS ESTIMATE
A65: HINGE | B65: Joinery | C65: Steel butt hinges 100 mm | D65: pair | E65: 75 | F65: QS ESTIMATE
A66: SFRAME | B66: Joinery | C66: Pressed steel door frame 813 | D66: no | E66: 680 | F66: QS ESTIMATE
A67: HWFRAME | B67: Joinery | C67: Hardwood external door frame | D67: no | E67: 1650 | F67: QS ESTIMATE
A68: LOCK3 | B68: Ironmongery | C68: 3-lever mortice lockset with handles | D68: no | E68: 320 | F68: QS ESTIMATE
A69: LOCK2 | B69: Ironmongery | C69: 2-lever mortice lockset with handles | D69: no | E69: 190 | F69: QS ESTIMATE
A70: CYLLOCK | B70: Ironmongery | C70: Cylinder lockset external | D70: no | E70: 650 | F70: QS ESTIMATE
A71: DSTOP | B71: Ironmongery | C71: Door stop | D71: no | E71: 45 | F71: QS ESTIMATE
A72: SKIRT | B72: Joinery | C72: Pine skirting 69 mm | D72: m | E72: 38 | F72: QS ESTIMATE
A73: BIC | B73: Joinery | C73: Built-in cupboards melamine full height — installed | D73: m | E73: 5200 | F73: QS ESTIMATE | G73: Per m run
A74: KITBASE | B74: Joinery | C74: Kitchen base units incl post-formed top — installed | D74: m | E74: 5800 | F74: QS ESTIMATE | G74: Per m run
A75: KITWALL | B75: Joinery | C75: Kitchen wall units — installed | D75: m | E75: 3900 | F75: QS ESTIMATE | G75: Per m run
A76: GRANITE | B76: Joinery | C76: Granite / quartz worktop 600 deep — installed | D76: m | E76: 3200 | F76: QS ESTIMATE | G76: Per m run
A77: STEELWIN | B77: Windows & doors | C77: Standard steel window incl glazing | D77: m2 | E77: 1350 | F77: QS ESTIMATE
A78: ALUWIN | B78: Windows & doors | C78: Aluminium casement, powder-coated, glazed | D78: m2 | E78: 2650 | F78: QS ESTIMATE
A79: ALUSLD | B79: Windows & doors | C79: Aluminium sliding door, safety glass | D79: m2 | E79: 3100 | F79: QS ESTIMATE
A80: ALUDOOR | B80: Windows & doors | C80: Aluminium hinged / French door, safety glass | D80: m2 | E80: 3400 | F80: QS ESTIMATE
A81: UPVCWIN | B81: Windows & doors | C81: uPVC window, glazed | D81: m2 | E81: 3300 | F81: QS ESTIMATE
A82: TIMWIN | B82: Windows & doors | C82: Meranti timber window, glazed | D82: m2 | E82: 2900 | F82: QS ESTIMATE
A83: BURGLAR | B83: Windows & doors | C83: Mild steel burglar bars, primed | D83: m2 | E83: 650 | F83: QS ESTIMATE
A84: SECGATE | B84: Windows & doors | C84: Trellis security gate | D84: m2 | E84: 1500 | F84: QS ESTIMATE
A85: GARAGE | B85: Windows & doors | C85: Sectional garage door 2.5x2.1 — installed | D85: no | E85: 16500 | F85: QS ESTIMATE
A86: GARMOTOR | B86: Windows & doors | C86: Garage door motor — installed | D86: no | E86: 6500 | F86: QS ESTIMATE
A87: GYP64 | B87: Ceilings & partitions | C87: Gypsum board 6.4 mm | D87: m2 | E87: 58 | F87: QS ESTIMATE
A88: GYP95 | B88: Ceilings & partitions | C88: Gypsum board 9.5 mm | D88: m2 | E88: 72 | F88: QS ESTIMATE
... A105: EPOXY | B105: Floor finishes | C105: Epoxy floor coating system | D105: m2 | E105: 165 | F105: QS ESTIMATE
A106: TILEFC | B106: Tiling | C106: Ceramic floor tile (PC) | D106: m2 | E106: 180 | F106: QS ESTIMATE | G106: Prime cost — adjust to client selection
A107: TILEPOR | B107: Tiling | C107: Porcelain floor tile 600x600 (PC) | D107: m2 | E107: 320 | F107: QS ESTIMATE | G107: Prime cost
A108: TILEWC | B108: Tiling | C108: Ceramic wall tile (PC) | D108: m2 | E108: 165 | F108: QS ESTIMATE | G108: Prime cost
A109: TILELF | B109: Tiling | C109: Large-format porcelain 600x1200 (PC) | D109: m2 | E109: 480 | F109: QS ESTIMATE | G109: Prime cost
A110: MOSAIC | B110: Tiling | C110: Mosaic tile on mesh (PC) | D110: m2 | E110: 520 | F110: QS ESTIMATE | G110: Prime cost
A111: SLATE | B111: Tiling | C111: Natural slate / stone paving (PC) | D111: m2 | E111: 260 | F111: QS ESTIMATE | G111: Prime cost
A112: ADH | B112: Tiling | C112: Tile adhesive, 20 kg bag | D112: bag | E112: 145 | F112: QS ESTIMATE
A113: GROUT | B113: Tiling | C113: Tile grout, 5 kg bag | D113: bag | E113: 95 | F113: QS ESTIMATE
A114: TRIM | B114: Tiling | C114: Aluminium tile trim | D114: m | E114: 42 | F114: QS ESTIMATE
A115: BEAD | B115: Plaster | C115: Galvanised angle bead | D115: m | E115: 14 | F115: QS ESTIMATE
A116: PVC110 | B116: Plumbing & drainage | C116: uPVC SN4 drain pipe 110 mm | D116: m | E116: 118 | F116: QS ESTIMATE
A117: PVC160 | B117: Plumbing & drainage | C117: uPVC SN4 drain pipe 160 mm | D117: m | E117: 240 | F117: QS ESTIMATE
A118: PVC50 | B118: Plumbing & drainage | C118: uPVC waste pipe 50 mm | D118: m | E118: 52 | F118: QS ESTIMATE
A119: PVC40 | B119: Plumbing & drainage | C119: uPVC waste pipe 40 mm | D119: m | E119: 38 | F119: QS ESTIMATE
...

Sheet Labour
A1: Code | B1: Grade / trade | C1: Basic wage R/hr | D1: Basis | E1: Source | F1: On-cost % | G1: All-in R/hr | H1: All-in R/day (9 h)
A2: L01 | B2: Labourer | C2: 41.33 | D2: PUBLISHED | E2: Cape Building Industry Bargaining Council main agreement, cl.18 (to 31 Oct 2026); BCCEI Grade 1 R41.72 | F2: =Settings!$B$17 -> 0.285 | G2: =C2*(1+F2) -> 53.10905 | H2: =G2*9 -> 477.98145
A3: L02 | B3: General worker (semi-skilled) | C3: 53.73 | D3: PUBLISHED | E3: Cape BIBC cl.18 | F3: =Settings!$B$17 -> 0.285 | G3: =C3*(1+F3) -> 69.04305 | H3: =G3*9 -> 621.38745
A4: L03 | B4: Tradesman Class 4 | C4: 58.49 | D4: PUBLISHED | E4: Cape BIBC cl.18 | F4: =Settings!$B$17 -> 0.285 | G4: =C4*(1+F4) -> 75.15965 | H4: =G4*9 -> 676.43685
A5: L04 | B5: Tradesman Class 3 (painter, paver, waterproofer) | C5: 64.52 | D5: PUBLISHED | E5: Cape BIBC cl.18 | F5: =Settings!$B$17 -> 0.285 | G5: =C5*(1+F5) -> 82.9082 | H5: =G5*9 -> 746.1738
A6: L05 | B6: Tradesman Class 2 (bricklayer, plasterer, tiler, shutterhand) | C6: 87.95 | D6: PUBLISHED | E6: Cape BIBC cl.18 | F6: =Settings!$B$17 -> 0.285 | G6: =C6*(1+F6) -> 113.01575 | H6: =G6*9 -> 1017.1418
A7: L06 | B7: Artisan (qualified carpenter / joiner / welder) | C7: 117.23 | D7: PUBLISHED | E7: Cape BIBC cl.18 | F7: =Settings!$B$17 -> 0.285 | G7: =C7*(1+F7) -> 150.64055 | H7: =G7*9 -> 1355.7649
A8: L07 | B8: Plant operator / driver Code C1 | C8: 73.41 | D8: PUBLISHED | E8: Cape BIBC cl.18 | F8: =Settings!$B$17 -> 0.285 | G8: =C8*(1+F8) -> 94.33185 | H8: =G8*9 -> 848.98665
A9: L08 | B9: Driver Code B | C9: 55.28 | D9: PUBLISHED | E9: Cape BIBC cl.18 | F9: =Settings!$B$17 -> 0.285 | G9: =C9*(1+F9) -> 71.0348 | H9: =G9*9 -> 639.3132
A10: L09 | B10: Electrician (registered, can issue COC) | C10: 140 | D10: QS ESTIMATE | E10: Market employed rate, 2026 | F10: =Settings!$B$17 -> 0.285 | G10: =C10*(1+F10) -> 179.9 | H10: =G10*9 -> 1619.1
A11: L10 | B11: Plumber (PIRB registered) | C11: 135 | D11: QS ESTIMATE | E11: Market employed rate, 2026 | F11: =Settings!$B$17 -> 0.285 | G11: =C11*(1+F11) -> 173.475 | H11: =G11*9 -> 1561.275
A12: L11 | B12: Site foreman | C12: 150 | D12: QS ESTIMATE | E12: Market, small-medium builder | F12: =Settings!$B$17 -> 0.285 | G12: =C12*(1+F12) -> 192.75 | H12: =G12*9 -> 1734.75
A13: L12 | B13: Site agent / contracts manager | C13: 240 | D13: QS ESTIMATE | E13: Market, small-medium builder | F13: =Settings!$B$17 -> 0.285 | G13: =C13*(1+F13) -> 308.4 | H13: =G13*9 -> 2775.6
A15: Reference: National Minimum Wage R30.23/hr from 1 March 2026 (GN R.7083, Gazette 54075). Bargaining council minima above sit higher and apply to formal building employers.
A16: Security guard (Cape BIBC) R495.34 per day basic — used in Preliminaries.

Sheet Gangs
A1: Gang | B1: Description | C1: Composition | D1: R per gang-hour
A2: G-LAB | B2: Labourer | C2: 1 x L01 | D2: =1*INDEX(Labour!$G:$G,MATCH("L01",Labour!$A:$A,0)) -> 53.10905
A3: G-SEM | B3: Semi-skilled general worker | C3: 1 x L02 | D3: =1*INDEX(Labour!$G:$G,MATCH("L02",Labour!$A:$A,0)) -> 69.04305
A4: G-DEM | B4: Demolition / strip-out gang | C4: 1 x L02 + 2 x L01 | D4: =1*INDEX(Labour!$G:$G,MATCH("L02",Labour!$A:$A,0))+2*INDEX(Labour!$G:$G,MATCH("L01",Labour!$A:$A,0)) -> 175.26115
A5: G-BRK | B5: Bricklayer + attendant | C5: 1 x L05 + 1 x L01 | D5: =1*INDEX(Labour!$G:$G,MATCH("L05",Labour!$A:$A,0))+1*INDEX(Labour!$G:$G,MATCH("L01",Labour!$A:$A,0)) -> 166.1248
A6: G-BRKF | B6: Face-brick artisan + attendant | C6: 1 x L06 + 1 x L01 | D6: =1*INDEX(Labour!$G:$G,MATCH("L06",Labour!$A:$A,0))+1*INDEX(Labour!$G:$G,MATCH("L01",Labour!$A:$A,0)) -> 203.7496
A7: G-CON | B7: Concrete gang | C7: 1 x L05 + 1 x L02 + 2 x L01 | D7: =1*INDEX(Labour!$G:$G,MATCH("L05",Labour!$A:$A,0))+1*INDEX(Labour!$G:$G,MATCH("L02",Labour!$A:$A,0))+2*INDEX(Labour!$G:$G,MATCH("L01",Labour!$A:$A,0)) -> 288.2769
A8: G-SHT | B8: Shutterhand + labourer | C8: 1 x L05 + 1 x L01 | D8: =1*INDEX(Labour!$G:$G,MATCH("L05",Labour!$A:$A,0))+1*INDEX(Labour!$G:$G,MATCH("L01",Labour!$A:$A,0)) -> 166.1248
A9: G-STF | B9: Steel fixer + labourer | C9: 1 x L05 + 1 x L01 | D9: =1*INDEX(Labour!$G:$G,MATCH("L05",Labour!$A:$A,0))+1*INDEX(Labour!$G:$G,MATCH("L01",Labour!$A:$A,0)) -> 166.1248
A10: G-CRP | B10: Carpenter + labourer | C10: 1 x L06 + 1 x L01 | D10: =1*INDEX(Labour!$G:$G,MATCH("L06",Labour!$A:$A,0))+1*INDEX(Labour!$G:$G,MATCH("L01",Labour!$A:$A,0)) -> 203.7496
A11: G-JNR | B11: Joiner | C11: 1 x L06 | D11: =1*INDEX(Labour!$G:$G,MATCH("L06",Labour!$A:$A,0)) -> 150.64055
A12: G-RFR | B12: Roofer + labourer | C12: 1 x L05 + 1 x L01 | D12: =1*INDEX(Labour!$G:$G,MATCH("L05",Labour!$A:$A,0))+1*INDEX(Labour!$G:$G,MATCH("L01",Labour!$A:$A,0)) -> 166.1248
A13: G-PLS | B13: Plasterer + labourer | C13: 1 x L05 + 1 x L01 | D13: =1*INDEX(Labour!$G:$G,MATCH("L05",Labour!$A:$A,0))+1*INDEX(Labour!$G:$G,MATCH("L01",Labour!$A:$A,0)) -> 166.1248
A14: G-SCR | B14: Screeder / finisher + labourer | C14: 1 x L05 + 1 x L01 | D14: =1*INDEX(Labour!$G:$G,MATCH("L05",Labour!$A:$A,0))+1*INDEX(Labour!$G:$G,MATCH("L01",Labour!$A:$A,0)) -> 166.1248
A15: G-TIL | B15: Tiler + half labourer | C15: 1 x L05 + 0.5 x L01 | D15: =1*INDEX(Labour!$G:$G,MATCH("L05",Labour!$A:$A,0))+0.5*INDEX(Labour!$G:$G,MATCH("L01",Labour!$A:$A,0)) -> 139.57028
A16: G-DRY | B16: Ceiling / drywall fixer + half worker | C16: 1 x L05 + 0.5 x L02 | D16: =1*INDEX(Labour!$G:$G,MATCH("L05",Labour!$A:$A,0))+0.5*INDEX(Labour!$G:$G,MATCH("L02",Labour!$A:$A,0)) -> 147.53727
A17: G-PNT | B17: Painter | C17: 1 x L04 | D17: =1*INDEX(Labour!$G:$G,MATCH("L04",Labour!$A:$A,0)) -> 82.9082
A18: G-WPF | B18: Waterproofer + labourer | C18: 1 x L04 + 1 x L01 | D18: =1*INDEX(Labour!$G:$G,MATCH("L04",Labour!$A:$A,0))+1*INDEX(Labour!$G:$G,MATCH("L01",Labour!$A:$A,0)) -> 136.01725
A19: G-GLZ | B19: Glazier / fixer | C19: 1 x L05 | D19: =1*INDEX(Labour!$G:$G,MATCH("L05",Labour!$A:$A,0)) -> 113.01575
A20: G-STW | B20: Steel erector gang | C20: 1 x L06 + 1 x L02 + 1 x L01 | D20: =1*INDEX(Labour!$G:$G,MATCH("L06",Labour!$A:$A,0))+1*INDEX(Labour!$G:$G,MATCH("L02",Labour!$A:$A,0))+1*INDEX(Labour!$G:$G,MATCH("L01",Labour!$A:$A,0)) -> 272.79265
A21: G-PLB | B21: Plumber + labourer | C21: 1 x L10 + 1 x L01 | D21: =1*INDEX(Labour!$G:$G,MATCH("L10",Labour!$A:$A,0))+1*INDEX(Labour!$G:$G,MATCH("L01",Labour!$A:$A,0)) -> 226.58405
A22: G-ELE | B22: Electrician + assistant | C22: 1 x L09 + 1 x L02 | D22: =1*INDEX(Labour!$G:$G,MATCH("L09",Labour!$A:$A,0))+1*INDEX(Labour!$G:$G,MATCH("L02",Labour!$A:$A,0)) -> 248.94305
A23: G-PAV | B23: Paving gang | C23: 1 x L04 + 2 x L01 | D23: =1*INDEX(Labour!$G:$G,MATCH("L04",Labour!$A:$A,0))+2*INDEX(Labour!$G:$G,MATCH("L01",Labour!$A:$A,0)) -> 189.1263
A24: G-FMN | B24: Site foreman | C24: 1 x L11 | D24: =1*INDEX(Labour!$G:$G,MATCH("L11",Labour!$A:$A,0)) -> 192.75
A25: G-SA | B25: Site agent | C25: 1 x L12 | D25: =1*INDEX(Labour!$G:$G,MATCH("L12",Labour!$A:$A,0)) -> 308.4

Sheet Plant
A1: Code | B1: Description | C1: Unit | D1: Rate ex VAT (R) | E1: Basis
A2: P-TLB | B2: TLB with operator & fuel | C2: hr | D2: 520 | E2: QS ESTIMATE
A3: P-EXC20 | B3: 20 t excavator with operator & fuel | C3: hr | D3: 1050 | E3: QS ESTIMATE
A4: P-JACK | B4: Compressor + jackhammer / breaker | C4: hr | D4: 150 | E4: QS ESTIMATE
A5: P-PLATE | B5: Plate compactor | C5: day | D5: 380 | E5: QS ESTIMATE
A6: P-ROLLER | B6: 1 t vibratory roller | C6: day | D6: 1400 | E6: QS ESTIMATE
A7: P-POKER | B7: Poker vibrator | C7: day | D7: 320 | E7: QS ESTIMATE
A8: P-MIXER | B8: 150 L concrete mixer | C8: day | D8: 300 | E8: QS ESTIMATE
A9: P-FLOAT | B9: Power float | C9: day | D9: 600 | E9: QS ESTIMATE
A10: P-SAW | B10: Floor saw | C10: day | D10: 700 | E10: QS ESTIMATE
A11: P-GRINDER | B11: Floor grinder | C11: day | D11: 1200 | E11: QS ESTIMATE
A12: P-CPUMP | B12: Concrete pump (per m3 pumped) | C12: m3 | D12: 170 | E12: QS ESTIMATE
A13: P-PROPS | B13: Props & soffit formwork hire per pour (3 weeks) | C13: m2 | D13: 45 | E13: QS ESTIMATE
... A22: P-CRANE | B22: 25 t mobile crane with operator | C22: day | D22: 9500 | E22: QS ESTIMATE

Sheet Regions
A1: Region | B1: Factor | C1: Basis / note
A2: Gauteng (Johannesburg / Pretoria / Midrand) - BASE | B2: 1 | C2: Base — AECOM rates are Gauteng-based.
A3: Western Cape - Cape Town metro & Winelands | B3: 1.08 | C3: AECOM: WC and KZN upper-class residential significantly above Gauteng. QS ESTIMATE.
A4: Western Cape - Garden Route / other | B4: 1.04 | C4: QS ESTIMATE.
A5: KwaZulu-Natal - Durban / Umhlanga / Ballito | B5: 1.04 | C5: AECOM regional note. QS ESTIMATE.
A6: KwaZulu-Natal - inland / other | B6: 0.98 | C6: QS ESTIMATE.
A7: Eastern Cape - Gqeberha / East London metros | B7: 0.97 | C7: Lower labour cost, comparable materials. QS ESTIMATE.
A8: Eastern Cape - rural (Transkei / Karoo interior) | B8: 1.06 | C8: Lower labour offset by haulage, no readymix, supervision travel. QS ESTIMATE.
A9: Free State - Bloemfontein | B9: 0.95 | C9: QS ESTIMATE.
A10: Free State - rural | B10: 0.98 | C10: QS ESTIMATE.
A11: Mpumalanga - Mbombela / Emalahleni | B11: 0.97 | C11: QS ESTIMATE.
A12: Limpopo - Polokwane | B12: 0.95 | C12: QS ESTIMATE.
A13: Limpopo - rural / remote | B13: 1.03 | C13: QS ESTIMATE.
... A16: Northern Cape - remote (Upington / Springbok) | B16: 1.08 | C16: Long-haul materials. QS ESTIMATE.

Sheet Elemental
A1: ELEMENTAL / ORDER-OF-MAGNITUDE BENCHMARKS (R/m2 construction area, ex VAT)
A2: Source: AECOM Africa Property & Construction Cost Guide 2025/26 pp.55-63 (rates at 1 July 2025, Gauteng). Include appropriate building services; exclude site infrastructure, parking (unless listed), escalation, professional fees and VAT. Escalated and region-adjusted by formula.
A4: Building type | B4: Unit | C4: AECOM low (Jul 2025) | D4: AECOM high (Jul 2025) | E4: Low — Sep 2026, region | F4: High — Sep 2026, region | G4: Mid — Sep 2026, region
A5: RESIDENTIAL
A6: RDP housing | B6: m2 | C6: 3400 | D6: 3600 | E6: =C6*Escalation!$B$20*Settings!$B$4*Settings!$B$9 -> 3568.2607 | F6: =D6*Escalation!$B$20*Settings!$B$4*Settings!$B$9 -> 3778.1584 | G6: =AVERAGE(E6:F6) -> 3673.2096
A7: Low-cost housing | B7: m2 | C7: 4300 | D7: 7400 | E7: =C7*Escalation!$B$20*Settings!$B$4*Settings!$B$9 -> 4512.8004 | F7: =D7*Escalation!$B$20*Settings!$B$4*Settings!$B$9 -> 7766.2146 | G7: =AVERAGE(E7:F7) -> 6139.5075
A8: Private dwelling — economic | B8: m2 | C8: 7920 | D8: 7920 | E8: =C8*Escalation!$B$20*Settings!$B$4*Settings!$B$9 -> 8311.9486 | F8: =D8*Escalation!$B$20*Settings!$B$4*Settings!$B$9 -> 8311.9486 | G8: =AVERAGE(E8:F8) -> 8311.9486
A9: Private dwelling — standard | B9: m2 | C9: 9850 | D9: 9850 | E9: =C9*Escalation!$B$20*Settings!$B$4*Settings!$B$9 -> 10337.461 | F9: =D9*Escalation!$B$20*Settings!$B$4*Settings!$B$9 -> 10337.461 | G9: =AVERAGE(E9:F9) -> 10337.461
A10: Private dwelling — middle-class | B10: m2 | C10: 11830 | D10: 11830 | E10: =C10*Escalation!$B$20*Settings!$B$4*Settings!$B$9 -> 12415.448 | F10: =D10*Escalation!$B$20*Settings!$B$4*Settings!$B$9 -> 12415.448 | G10: =AVERAGE(E10:F10) -> 12415.448
A11: Private dwelling — luxury | B11: m2 | C11: 16350 | D11: 16350 | E11: =C11*Escalation!$B$20*Settings!$B$4*Settings!$B$9 -> 17159.136 | F11: =D11*Escalation!$B$20*Settings!$B$4*Settings!$B$9 -> 17159.136 | G11: =AVERAGE(E11:F11) -> 17159.136
A12: Private dwelling — exclusive | B12: m2 | C12: 26450 | D12: 26450 | E12: =C12*Escalation!$B$20*Settings!$B$4*Settings!$B$9 -> 27758.97 | F12: =D12*Escalation!$B$20*Settings!$B$4*Settings!$B$9 -> 27758.97 | G12: =AVERAGE(E12:F12) -> 27758.97
A13: Private dwelling — super luxury | B13: m2 | C13: 38000 | D13: 80000 | E13: =C13*Escalation!$B$20*Settings!$B$4*Settings!$B$9 -> 39880.561 | F13: =D13*Escalation!$B$20*Settings!$B$4*Settings!$B$9 -> 83959.076 | G13: =AVERAGE(E13:F13) -> 61919.819
A14: Outbuildings — standard | B14: m2 | C14: 7400 | D14: 7400 | E14: =C14*Escalation!$B$20*Settings!$B$4*Settings!$B$9 -> 7766.2146 | F14: =D14*Escalation!$B$20*Settings!$B$4*Settings!$B$9 -> 7766.2146 | G14: =AVERAGE(E14:F14) -> 7766.2146
A15: Outbuildings — luxury | B15: m2 | C15: 10400 | D15: 10400 | E15: =C15*Escalation!$B$20*Settings!$B$4*Settings!$B$9 -> 10914.68 | F15: =D15*Escalation!$B$20*Settings!$B$4*Settings!$B$9 -> 10914.68 | G15: =AVERAGE(E15:F15) -> 10914.68
A16: Simple low-rise apartment block | B16: m2 | C16: 10300 | D16: 14300 | E16: =C16*Escalation!$B$20*Settings!$B$4*Settings!$B$9 -> 10809.731 | F16: =D16*Escalation!$B$20*Settings!$B$4*Settings!$B$9 -> 15007.685 | G16: =AVERAGE(E16:F16) -> 12908.708
A17: Duplex townhouse — economic | B17: m2 | C17: 10300 | D17: 14700 | E17: =C17*Escalation!$B$20*Settings!$B$4*Settings!$B$9 -> 10809.731 | F17: =D17*Escalation!$B$20*Settings!$B$4*Settings!$B$9 -> 15427.48 | G17: =AVERAGE(E17:F17) -> 13118.606
... A30: Tennis court — standard | B30: no | C30: 710000 | D30: 710000 | E30: =C30*Escalation!$B$20*Settings!$B$4*Settings!$B$9 -> 745136.8 | F30: =D30*Escalation!$B$20*Settings!$B$4*Settings!$B$9 -> 745136.8 | G30: =AVERAGE(E30:F30) -> 745136.8
A31: COMMERCIAL / RETAIL
A32: Low-rise office park, standard | B32: m2 | C32: 11300 | D32: 13900 | E32: =C32*Escalation!$B$20*Settings!$B$4*Settings!$B$9 -> 11859.22 | F32: =D32*Escalation!$B$20*Settings!$B$4*Settings!$B$9 -> 14587.89 | G32: =AVERAGE(E32:F32) -> 13223.555
A33: Low-rise office park, prestige | B33: m2 | C33: 14600 | D33: 21700 | E33: =C33*Escalation!$B$20*Settings!$B$4*Settings!$B$9 -> 15322.531 | F33: =D33*Escalation!$B$20*Settings!$B$4*Settings!$B$9 -> 22773.899 | G33: =AVERAGE(E33:F33) -> 19048.215
A34: High-rise office, standard | B34: m2 | C34: 16400 | D34: 21700 | E34: =C34*Escalation!$B$20*Settings!$B$4*Settings!$B$9 -> 17211.611 | F34: =D34*Escalation!$B$20*Settings!$B$4*Settings!$B$9 -> 22773.899 | G34: =AVERAGE(E34:F34) -> 19992.755
A35: High-rise office, prestige | B35: m2 | C35: 21700 | D35: 27400 | E35: =C35*Escalation!$B$20*Settings!$B$4*Settings!$B$9 -> 22773.899 | F35: =D35*Escalation!$B$20*Settings!$B$4*Settings!$B$9 -> 28755.984 | G35: =AVERAGE(E35:F35) -> 25764.942
A36: Local convenience centre <= 5,000 m2 | B36: m2 | C36: 11100 | D36: 14600 | E36: =C36*Escalation!$B$20*Settings!$B$4*Settings!$B$9 -> 11649.322 | F36: =D36*Escalation!$B$20*Settings!$B$4*Settings!$B$9 -> 15322.531 | G36: =AVERAGE(E36:F36) -> 13485.927
A37: Neighbourhood centre 5,000-12,000 m2 | B37: m2 | C37: 12100 | D37: 16100 | E37: =C37*Escalation!$B$20*Settings!$B$4*Settings!$B$9 -> 12698.81 | F37: =D37*Escalation!$B$20*Settings!$B$4*Settings!$B$9 -> 16896.764 | G37: =AVERAGE(E37:F37) -> 14797.787
A38: Community centre 12,000-25,000 m2 | B38: m2 | C38: 13300 | D38: 17100 | E38: =C38*Escalation!$B$20*Settings!$B$4*Settings!$B$9 -> 13958.196 | F38: =D38*Escalation!$B$20*Settings!$B$4*Settings!$B$9 -> 17946.253 | G38: =AVERAGE(E38:F38) -> 15952.225
A39: Studios (dance, art exhibition) | B39: m2 | C39: 19500 | D39: 28000 | E39: =C39*Escalation!$B$20*Settings!$B$4*Settings!$B$9 -> 20465.025 | F39: =D39*Escalation!$B$20*Settings!$B$4*Settings!$B$9 -> 29385.677 | G39: =AVERAGE(E39:F39) -> 24925.351
A40: Conference centre, international standard | B40: m2 | C40: 36000 | D40: 46000 | E40: =C40*Escalation!$B$20*Settings!$B$4*Settings!$B$9 -> 37781.584 | F40: =D40*Escalation!$B$20*Settings!$B$4*Settings!$B$9 -> 48276.469 | G40: =AVERAGE(E40:F40) -> 43029.027
A41: INDUSTRIAL
A42: Warehouse, steel frame & cladding (light duty) | B42: m2 | C42: 5800 | D42: 7400 | E42: =C42*Escalation!$B$20*Settings!$B$4*Settings!$B$9 -> 6087.033 | F42: =D42*Escalation!$B$20*Settings!$B$4*Settings!$B$9 -> 7766.2146 | G42: =AVERAGE(E42:F42) -> 6926.6238
A43: Warehouse, brick to ceiling + cladding (heavy duty) | B43: m2 | C43: 6500 | D43: 9300 | E43: =C43*Escalation!$B$20*Settings!$B$4*Settings!$B$9 -> 6821.675 | F43: =D43*Escalation!$B$20*Settings!$B$4*Settings!$B$9 -> 9760.2426 | G43: =AVERAGE(E43:F43) -> 8290.9588
A44: Admin offices / ablution / change block | B44: m2 | C44: 10500 | D44: 13400 | E44: =C44*Escalation!$B$20*Settings!$B$4*Settings!$B$9 -> 11019.629 | F44: =D44*Escalation!$B$20*Settings!$B$4*Settings!$B$9 -> 14063.145 | G44: =AVERAGE(E44:F44) -> 12541.387
A45: Cold storage | B45: m2 | C45: 19600 | D45: 27900 | E45: =C45*Escalation!$B$20*Settings!$B$4*Settings!$B$9 -> 20569.974 | F45: =D45*Escalation!$B$20*Settings!$B$4*Settings!$B$9 -> 29280.728 | G45: =AVERAGE(E45:F45) -> 24925.351
A46: PARKING
A47: Parking on grade incl landscaping | B47: m2 | C47: 800 | D47: 1000 | E47: =C47*Escalation!$B$20*Settings!$B$4*Settings!$B$9 -> 839.59076 | F47: =D47*Escalation!$B$20*Settings!$B$4*Settings!$B$9 -> 1049.4885 | G47: =AVERAGE(E47:F47) -> 944.53961
A48: Structured parking | B48: m2 | C48: 5500 | D48: 6100 | E48: =C48*Escalation!$B$20*Settings!$B$4*Settings!$B$9 -> 5772.1865 | F48: =D48*Escalation!$B$20*Settings!$B$4*Settings!$B$9 -> 6401.8796 | G48: =AVERAGE(E48:F48) -> 6087.033
A49: Semi-basement parking | B49: m2 | C49: 6100 | D49: 8300 | E49: =C49*Escalation!$B$20*Settings!$B$4*Settings!$B$9 -> 6401.8796 | F49: =D49*Escalation!$B$20*Settings!$B$4*Settings!$B$9 -> 8710.7542 | G49: =AVERAGE(E49:F49) -> 7556.3169
A50: Basement parking | B50: m2 | C50: 6500 | D50: 11300 | E50: =C50*Escalation!$B$20*Settings!$B$4*Settings!$B$9 -> 6821.675 | F50: =D50*Escalation!$B$20*Settings!$B$4*Settings!$B$9 -> 11859.22 | G50: =AVERAGE(E50:F50) -> 9340.4473
A51: SOCIAL
A52: Primary school | B52: m2 | C52: 9300 | D52: 10700 | E52: =C52*Escalation!$B$20*Settings!$B$4*Settings!$B$9 -> 9760.2426 | F52: =D52*Escalation!$B$20*Settings!$B$4*Settings!$B$9 -> 11229.526 | G52: =AVERAGE(E52:F52) -> 10494.885
A53: Secondary school | B53: m2 | C53: 11100 | D53: 11900 | E53: =C53*Escalation!$B$20*Settings!$B$4*Settings!$B$9 -> 11649.322 | F53: =D53*Escalation!$B$20*Settings!$B$4*Settings!$B$9 -> 12488.913 | G53: =AVERAGE(E53:F53) -> 12069.117
A54: District hospital (excl FF&E) | B54: m2 | C54: 39000 | D54: 39000 | E54: =C54*Escalation!$B$20*Settings!$B$4*Settings!$B$9 -> 40930.05 | F54: =D54*Escalation!$B$20*Settings!$B$4*Settings!$B$9 -> 40930.05 | G54: =AVERAGE(E54:F54) -> 40930.05
A55: Hotel — budget (incl FF&E) | B55: key | C55: 890000 | D55: 1400000 | E55: =C55*Escalation!$B$20*Settings!$B$4*Settings!$B$9 -> 934044.73 | F55: =D55*Escalation!$B$20*Settings!$B$4*Settings!$B$9 -> 1469283.8 | G55: =AVERAGE(E55:F55) -> 1201664.3
A56: Hotel — 3-star (incl FF&E) | B56: key | C56: 1401000 | D56: 2100000 | E56: =C56*Escalation!$B$20*Settings!$B$4*Settings!$B$9 -> 1470333.3 | F56: =D56*Escalation!$B$20*Settings!$B$4*Settings!$B$9 -> 2203925.8 | G56: =AVERAGE(E56:F56) -> 1837129.5
A57: SERVICES (R/m2 GFA)
A58: Electrical — residential | B58: m2 | C58: 950 | D58: 1600 | E58: =C58*Escalation!$B$20*Settings!$B$4*Settings!$B$9 -> 997.01403 | F58: =D58*Escalation!$B$20*Settings!$B$4*Settings!$B$9 -> 1679.1815 | G58: =AVERAGE(E58:F58) -> 1338.0978
A59: Electrical — offices standard | B59: m2 | C59: 1100 | D59: 1600 | E59: =C59*Escalation!$B$20*Settings!$B$4*Settings!$B$9 -> 1154.4373 | F59: =D59*Escalation!$B$20*Settings!$B$4*Settings!$B$9 -> 1679.1815 | G59: =AVERAGE(E59:F59) -> 1416.8094
A60: Electronic (access, CCTV, fire detection, data) — residential | B60: m2 | C60: 450 | D60: 750 | E60: =C60*Escalation!$B$20*Settings!$B$4*Settings!$B$9 -> 472.2698 | F60: =D60*Escalation!$B$20*Settings!$B$4*Settings!$B$9 -> 787.11634 | G60: =AVERAGE(E60:F60) -> 629.69307
A61: Air-conditioning — residential split units | B61: m2 | C61: 1350 | D61: 2100 | E61: =C61*Escalation!$B$20*Settings!$B$4*Settings!$B$9 -> 1416.8094 | F61: =D61*Escalation!$B$20*Settings!$B$4*Settings!$B$9 -> 2203.9258 | G61: =AVERAGE(E61:F61) -> 1810.3676
A62: Air-conditioning — offices split | B62: m2 | C62: 1350 | D62: 2150 | E62: =C62*Escalation!$B$20*Settings!$B$4*Settings!$B$9 -> 1416.8094 | F62: =D62*Escalation!$B$20*Settings!$B$4*Settings!$B$9 -> 2256.4002 | G62: =AVERAGE(E62:F62) -> 1836.6048
A63: Sprinklers incl hydrants & hose reels (offices) | B63: m2 | C63: 450 | D63: 600 | E63: =C63*Escalation!$B$20*Settings!$B$4*Settings!$B$9 -> 472.2698 | F63: =D63*Escalation!$B$20*Settings!$B$4*Settings!$B$9 -> 629.69307 | G63: =AVERAGE(E63:F63) -> 550.98144
A65: Benchmarks are the contractor's tender price (they include contractor OH&P) — compare BOQ totals INCLUDING the 17% margin, ex VAT.

Sheet Escalation
A1: BUILDING COST INDICES (Jan 2020 = 100)
A2: Source: AECOM Africa Property & Construction Cost Guide 2025/26, Section 7 — BER (Stellenbosch) tender price index and Stats SA P0151 CPAP Work Group 181. 2026-2029 are forecasts.
A4: Year (Jan) | B4: BER tender index | C4: BER y-o-y | D4: CPAP WG181 index | E4: CPAP y-o-y | F4: Tender Market Indicator
A5: 2020 | B5: 100 | D5: 100 | F5: 1
A6: 2021 | B6: 102.4 | C6: 0.024 | D6: 106 | E6: 0.06 | F6: 0.97
A7: 2022 | B7: 108.1 | C7: 0.056 | D7: 120.9 | E7: 0.141 | F7: 0.89
A8: 2023 | B8: 119.1 | C8: 0.101 | D8: 128.4 | E8: 0.062 | F8: 0.93
A9: 2024 | B9: 136.7 | C9: 0.148 | D9: 135.1 | E9: 0.052 | F9: 1.01
A10: 2025 | B10: 145.7 | C10: 0.066 | D10: 137.8 | E10: 0.02 | F10: 1.06
A11: 2026 | B11: 150.9 | C11: 0.036 | D11: 144 | E11: 0.045 | F11: 1.05
A12: 2027 | B12: 158 | C12: 0.047 | D12: 150.7 | E12: 0.046 | F12: 1.05
A13: 2028 | B13: 166.9 | C13: 0.056 | D13: 157.3 | E13: 0.044 | F13: 1.06
A14: 2029 | B14: 176.7 | C14: 0.059 | D14: 164.2 | E14: 0.044 | F14: 1.08
A17: Escalation of AECOM 1 July 2025 benchmarks to library base date (Sep 2026)
A18: Jul 2025 -> Jan 2026 (6 months at 2026 y-o-y) | B18: =(1+C11)^(6/12) -> 1.0178409
A19: Jan 2026 -> Sep 2026 (8 months at 2027 y-o-y) | B19: =(1+C12)^(8/12) -> 1.0310929
A20: Factor AECOM Jul-2025 -> Sep-2026 | B20: =B18*B19 -> 1.0494885

Sheet Calibration
A1: CALIBRATION — library sell rates vs published 2026 SA market ranges
A2: Consumer guides quote builder prices that usually include higher OH&P and sometimes VAT, so library sell rates (17% margin, ex VAT) are expected to sit low-to-mid in range.
A4: Code | B4: Item | C4: Compared | D4: Market low | E4: Market high | F4: Library sell | G4: Position | H4: Source
A5: MS01 | B5: Half-brick wall | C5: Labour only | D5: 150 | E5: 270 | F5: =INDEX(Rates!$F:$F,MATCH(A5,Rates!$A:$A,0))*Settings!$B$4*Settings!$B$9*(1+Settings!$B$10) -> 165.21111 | G5: =IF(F5<D5,"Below range",IF(F5>E5,"Above range","In range")) -> In range | H5: sapropertytools.co.za bricklaying calculator, June 2026
A6: MS02 | B6: One-brick wall | C6: Labour only | D6: 300 | E6: 510 | F6: =INDEX(Rates!$F:$F,MATCH(A6,Rates!$A:$A,0))*Settings!$B$4*Settings!$B$9*(1+Settings!$B$10) -> 310.98563 | G6: =IF(F6<D6,"Below range",IF(F6>E6,"Above range","In range")) -> In range | H6: sapropertytools.co.za, June 2026
A7: TL01 | B7: Floor tiling | C7: Labour only | D7: 110 | E7: 200 | F7: =INDEX(Rates!$F:$F,MATCH(A7,Rates!$A:$A,0))*Settings!$B$4*Settings!$B$9*(1+Settings!$B$10) -> 130.63778 | G7: =IF(F7<D7,"Below range",IF(F7>E7,"Above range","In range")) -> In range | H7: sapropertytools.co.za tiling calculator, June 2026
A8: TL03 | B8: Wall tiling | C8: Labour only | D8: 140 | E8: 240 | F8: =INDEX(Rates!$F:$F,MATCH(A8,Rates!$A:$A,0))*Settings!$B$4*Settings!$B$9*(1+Settings!$B$10) -> 163.29722 | G8: =IF(F8<D8,"Below range",IF(F8>E8,"Above range","In range")) -> In range | H8: sapropertytools.co.za, June 2026
A9: PL01 | B9: Two-coat internal plaster | C9: Labour only | D9: 85 | E9: 130 | F9: =INDEX(Rates!$F:$F,MATCH(A9,Rates!$A:$A,0))*Settings!$B$4*Settings!$B$9*(1+Settings!$B$10) -> 87.464707 | G9: =IF(F9<D9,"Below range",IF(F9>E9,"Above range","In range")) -> In range | H9: sapropertytools.co.za plastering calculator, June 2026
A10: PL01 | B10: Two-coat internal plaster | C10: All-in | D10: 90 | E10: 160 | F10: =INDEX(Rates!$T:$T,MATCH(A10,Rates!$A:$A,0)) -> 111.59069 | G10: =IF(F10<D10,"Below range",IF(F10>E10,"Above range","In range")) -> In range | H10: sapropertytools.co.za plastering & painting guide, July 2026
A11: PT01 | B11: Interior painting | C11: Labour only | D11: 25 | E11: 60 | F11: =INDEX(Rates!$F:$F,MATCH(A11,Rates!$A:$A,0))*Settings!$B$4*Settings!$B$9*(1+Settings!$B$10) -> 29.100778 | G11: =IF(F11<D11,"Below range",IF(F11>E11,"Above range","In range")) -> In range | H11: sapropertytools.co.za, July 2026
A12: RF01 | B12: Roof trusses excl covering | C12: All-in | D12: 250 | E12: 650 | F12: =INDEX(Rates!$T:$T,MATCH(A12,Rates!$A:$A,0)) -> 522.62416 | G12: =IF(F12<D12,"Below range",IF(F12>E12,"Above range","In range")) -> In range | H12: completeroofing.co.za, Feb 2026
A13: RF04 | B13: Concrete tile covering | C13: All-in | D13: 500 | E13: 800 | F13: =INDEX(Rates!$T:$T,MATCH(A13,Rates!$A:$A,0)) -> 445.72591 | G13: =IF(F13<D13,"Below range",IF(F13>E13,"Above range","In range")) -> Below range | H13: thehandymanjohannesburg.co.za, 2026 (JHB, typically incl VAT)
A14: RF06 | B14: IBR sheeting covering | C14: All-in | D14: 150 | E14: 350 | F14: =INDEX(Rates!$T:$T,MATCH(A14,Rates!$A:$A,0)) -> 313.9548 | G14: =IF(F14<D14,"Below range",IF(F14>E14,"Above range","In range")) -> In range | H14: servicelinksa.co.za, Mar 2026 (covering only)

Sheet Sources
A1: SOURCES
A3: AECOM Africa Property & Construction Cost Guide 2025/26 (36th ed.) — SA building cost rates, services rates, BER/CPAP indices | B3: https://cdn.ymaws.com/www.asaqs.co.za/resource/resmgr/4_resources/free_resources/other_publications/aecom_africa_cost_guide_2025.pdf
A4: National Minimum Wage R30.23/hr from 1 March 2026 (GN R.7083, Gazette 54075) | B4: https://www.sanews.gov.za/south-africa/national-minimum-wage-rise-r3023-hour-march
A5: Bargaining Council for the Building Industry, Cape of Good Hope — Main Agreement cl.18 minimum wages (to 31 Oct 2026) | B5: https://www.acts.co.za/labour/r6498_18__minimum_basic_wages
A6: BCCEI Civil Engineering task-grade minimum wages (WageIndicator, 2026) | B6: https://wageindicator.org/en-za/work-in-south-africa/minimum-wage/6228-civil-engineering-sector
A7: SA Property Tools — 2026 bricklaying / tiling / plastering labour rate benchmarks | B7: https://sapropertytools.co.za/calculators/artisan/bricklaying-labour.html
A8: SA Property Tools — Plastering & painting cost guide 2026 | B8: https://sapropertytools.co.za/blog/plastering-painting-guide-sa.html
A9: Handyman Johannesburg — Building material prices 2026 (cement, sand, stone, readymix, bricks) | B9: https://www.thehandymanjohannesburg.co.za/building-material-prices/
A10: Complete Roofing — roof truss prices per m2 (2026) | B10: https://completeroofing.co.za/blog/roof-trusses-prices-per-m2/
A11: PPC mix guidance via South Africa Facts concrete calculator (Aug 2026) | B11: https://southafricafacts.co.za/concrete-mortar-calculator-south-africa/
A12: Stats SA P0151 Contract Price Adjustment Provisions indices (for escalation claims) | B12: https://www.statssa.gov.za
A13: ASAQS Standard System of Measuring Building Work (trade order used for descriptions) | B13: https://www.asaqs.co.za
